{
  "type": "Feature",
  "properties": {
    "gn:admin1_code":"00",
    "gn:asciiname":"Bileosi",
    "gn:country_code":"GQ",
    "gn:dem":668,
    "gn:feature_class":"P",
    "gn:feature_code":"PPL",
    "gn:name":"Bileosi",
    "gn:population":0,
    "gn:timezone":"Africa/Malabo",
    "iso:country":"GQ",
    "wof:name":"Bileosi",
    "wof:placetype":"locality"
},
  "geometry": {"coordinates":[11.26619,1.68541],"type":"Point"}
}