{
  "type": "Feature",
  "properties": {
    "gn:admin1_code":"00",
    "gn:asciiname":"Mbabiyegue",
    "gn:country_code":"GQ",
    "gn:dem":24,
    "gn:feature_class":"P",
    "gn:feature_code":"PPL",
    "gn:name":"Mbabiyegue",
    "gn:population":0,
    "gn:timezone":"Africa/Malabo",
    "iso:country":"GQ",
    "wof:name":"Mbabiyegue",
    "wof:placetype":"locality"
},
  "geometry": {"coordinates":[9.93234,1.00182],"type":"Point"}
}