{
  "type": "Feature",
  "properties": {
    "gn:admin1_code":"00",
    "gn:asciiname":"Mabesan",
    "gn:country_code":"GQ",
    "gn:dem":438,
    "gn:feature_class":"P",
    "gn:feature_code":"PPL",
    "gn:name":"Mabesan",
    "gn:population":0,
    "gn:timezone":"Africa/Malabo",
    "iso:country":"GQ",
    "wof:name":"Mabesan",
    "wof:placetype":"locality"
},
  "geometry": {"coordinates":[10.63471,1.90757],"type":"Point"}
}