{
  "type": "Feature",
  "properties": {
    "gn:admin1_code":"00",
    "gn:asciiname":"Ecoguong",
    "gn:country_code":"GQ",
    "gn:dem":401,
    "gn:feature_class":"P",
    "gn:feature_code":"PPL",
    "gn:name":"Ecoguong",
    "gn:population":0,
    "gn:timezone":"Africa/Malabo",
    "iso:country":"GQ",
    "wof:name":"Ecoguong",
    "wof:placetype":"locality"
},
  "geometry": {"coordinates":[10.30868,1.99119],"type":"Point"}
}