{
  "type": "Feature",
  "properties": {
    "gn:admin1_code":"00",
    "gn:asciiname":"Movo",
    "gn:country_code":"GQ",
    "gn:dem":48,
    "gn:feature_class":"P",
    "gn:feature_code":"PPL",
    "gn:name":"Mov\u00f3",
    "gn:population":0,
    "gn:timezone":"Africa/Malabo",
    "iso:country":"GQ",
    "wof:name":"Movo",
    "wof:placetype":"locality"
},
  "geometry": {"coordinates":[9.62255,1.14392],"type":"Point"}
}