{
  "type": "Feature",
  "properties": {
    "gn:admin1_code":"00",
    "gn:asciiname":"Macom",
    "gn:country_code":"GQ",
    "gn:dem":663,
    "gn:feature_class":"P",
    "gn:feature_code":"PPL",
    "gn:name":"Macom",
    "gn:population":0,
    "gn:timezone":"Africa/Malabo",
    "iso:country":"GQ",
    "name:und_x_variant":[
        "Mokom",
        "Macom"
    ],
    "wof:name":"Macom",
    "wof:placetype":"locality"
},
  "geometry": {"coordinates":[11.33635,1.65013],"type":"Point"}
}