{
  "type": "Feature",
  "properties": {
    "gn:admin1_code":"00",
    "gn:asciiname":"Ngong",
    "gn:country_code":"GQ",
    "gn:dem":634,
    "gn:feature_class":"P",
    "gn:feature_code":"PPL",
    "gn:name":"Ngong",
    "gn:population":0,
    "gn:timezone":"Africa/Malabo",
    "iso:country":"GQ",
    "name:und_x_variant":[
        "Ndgong",
        "Ngong"
    ],
    "wof:name":"Ngong",
    "wof:placetype":"locality"
},
  "geometry": {"coordinates":[10.41633,1.42515],"type":"Point"}
}