{
  "type": "Feature",
  "properties": {
    "gn:admin1_code":"00",
    "gn:asciiname":"Bocondo",
    "gn:country_code":"GQ",
    "gn:dem":399,
    "gn:feature_class":"P",
    "gn:feature_code":"PPL",
    "gn:name":"Bocondo",
    "gn:population":0,
    "gn:timezone":"Africa/Malabo",
    "iso:country":"GQ",
    "wof:name":"Bocondo",
    "wof:placetype":"locality"
},
  "geometry": {"coordinates":[10.35799,2.01205],"type":"Point"}
}