{
  "type": "Feature",
  "properties": {
    "gn:admin1_code":"00",
    "gn:asciiname":"Malancha",
    "gn:country_code":"GQ",
    "gn:dem":12,
    "gn:feature_class":"P",
    "gn:feature_code":"PPL",
    "gn:name":"Malancha",
    "gn:population":0,
    "gn:timezone":"Africa/Malabo",
    "iso:country":"GQ",
    "wof:name":"Malancha",
    "wof:placetype":"locality"
},
  "geometry": {"coordinates":[9.4504,1.119],"type":"Point"}
}