{
  "type": "Feature",
  "properties": {
    "gn:admin1_code":"00",
    "gn:asciiname":"Ndyengmiang",
    "gn:country_code":"GQ",
    "gn:dem":36,
    "gn:feature_class":"P",
    "gn:feature_code":"PPL",
    "gn:name":"Ndyengmiang",
    "gn:population":0,
    "gn:timezone":"Africa/Malabo",
    "iso:country":"GQ",
    "wof:name":"Ndyengmiang",
    "wof:placetype":"locality"
},
  "geometry": {"coordinates":[9.374,1.14868],"type":"Point"}
}