{
  "type": "Feature",
  "properties": {
    "gn:admin1_code":"00",
    "gn:asciiname":"Ngong",
    "gn:country_code":"GQ",
    "gn:dem":647,
    "gn:feature_class":"P",
    "gn:feature_code":"PPL",
    "gn:name":"Ngong",
    "gn:population":0,
    "gn:timezone":"Africa/Malabo",
    "iso:country":"GQ",
    "name:ceb_x_preferred":[
        "Ngong"
    ],
    "name:deu_x_preferred":[
        "Ngong"
    ],
    "name:swe_x_preferred":[
        "Ngong"
    ],
    "wof:name":"Ngong",
    "wof:placetype":"locality"
},
  "geometry": {"coordinates":[10.58204,1.26339],"type":"Point"}
}