{
  "type": "Feature",
  "properties": {
    "gn:admin1_code":"00",
    "gn:asciiname":"Akelayong",
    "gn:country_code":"GQ",
    "gn:dem":100,
    "gn:feature_class":"P",
    "gn:feature_code":"PPL",
    "gn:name":"Akelayong",
    "gn:population":0,
    "gn:timezone":"Africa/Malabo",
    "iso:country":"GQ",
    "wof:name":"Akelayong",
    "wof:placetype":"locality"
},
  "geometry": {"coordinates":[9.88709,1.19513],"type":"Point"}
}