{
  "type": "Feature",
  "properties": {
    "gn:admin1_code":"00",
    "gn:asciiname":"Mocuu",
    "gn:country_code":"GQ",
    "gn:dem":135,
    "gn:feature_class":"P",
    "gn:feature_code":"PPL",
    "gn:name":"Mocuu",
    "gn:population":0,
    "gn:timezone":"Africa/Malabo",
    "iso:country":"GQ",
    "wof:name":"Mocuu",
    "wof:placetype":"locality"
},
  "geometry": {"coordinates":[10.01483,2.13554],"type":"Point"}
}