{
  "type": "Feature",
  "properties": {
    "gn:admin1_code":"00",
    "gn:asciiname":"Obenelang",
    "gn:country_code":"GQ",
    "gn:dem":383,
    "gn:feature_class":"P",
    "gn:feature_code":"PPL",
    "gn:name":"Obenelang",
    "gn:population":0,
    "gn:timezone":"Africa/Malabo",
    "iso:country":"GQ",
    "name:und_x_variant":[
        "Abenelang",
        "Obenelang"
    ],
    "wof:name":"Obenelang",
    "wof:placetype":"locality"
},
  "geometry": {"coordinates":[10.41109,1.87803],"type":"Point"}
}