{
  "type": "Feature",
  "properties": {
    "iso:country":"GQ",
    "name:cat_x_preferred":[
        "San Antonio de Pal\u00e9"
    ],
    "name:ceb_x_preferred":[
        "Pal\u00e9"
    ],
    "name:deu_x_preferred":[
        "San Antonio de Pal\u00e9"
    ],
    "name:eng_x_historical":[
        "St Antony",
        "San Antonio de Praia"
    ],
    "name:eng_x_preferred":[
        "San Antonio de Pal\u00e9"
    ],
    "name:eng_x_variant":[
        "St Antony",
        "San Antonio de Praia"
    ],
    "name:est_x_preferred":[
        "San Antonio de Pal\u00e9"
    ],
    "name:est_x_variant":[
        "Pagalu"
    ],
    "name:eus_x_preferred":[
        "Pale"
    ],
    "name:fin_x_preferred":[
        "San Antonio de Pal\u00e9"
    ],
    "name:fra_x_preferred":[
        "San Antonio de Pal\u00e9"
    ],
    "name:frr_x_preferred":[
        "San Antonio de Pal\u00e9"
    ],
    "name:heb_x_preferred":[
        "\u05e1\u05df \u05d0\u05e0\u05d8\u05d5\u05e0\u05d9\u05d5 \u05d3\u05d4 \u05e4\u05d0\u05dc\u05d4"
    ],
    "name:ita_x_preferred":[
        "San Antonio de Pal\u00e9"
    ],
    "name:jpn_x_preferred":[
        "\u30b5\u30f3\u30a2\u30f3\u30c8\u30cb\u30aa\u30fb\u30c7\u30fb\u30d1\u30ec"
    ],
    "name:kat_x_preferred":[
        "\u10e1\u10d0\u10dc-\u10d0\u10dc\u10e2\u10dd\u10dc\u10d8\u10dd-\u10d3\u10d4-\u10de\u10d0\u10da\u10d4"
    ],
    "name:kor_x_preferred":[
        "\uc0b0\uc548\ud1a0\ub2c8\uc624\ub370\ud314\ub808"
    ],
    "name:lit_x_preferred":[
        "San Antonijo de Pal\u0117"
    ],
    "name:nld_x_preferred":[
        "San Antonio de Pal\u00e9"
    ],
    "name:nob_x_preferred":[
        "San Antonio de Pal\u00e9"
    ],
    "name:pol_x_preferred":[
        "Pagalu"
    ],
    "name:por_x_preferred":[
        "San Antonio de Pal\u00e9"
    ],
    "name:rus_x_preferred":[
        "\u0421\u0430\u043d-\u0410\u043d\u0442\u043e\u043d\u0438\u043e-\u0434\u0435-\u041f\u0430\u043b\u0435"
    ],
    "name:sco_x_preferred":[
        "San Antonio de Pal\u00e9"
    ],
    "name:spa_x_preferred":[
        "San Antonio de Pal\u00e9"
    ],
    "name:srp_x_preferred":[
        "\u0421\u0430\u043d \u0410\u043d\u0442\u043e\u043d\u0438\u043e \u0434\u0435 \u041f\u0430\u043b\u0435"
    ],
    "name:swe_x_preferred":[
        "Pal\u00e9"
    ],
    "name:tha_x_preferred":[
        "\u0e0b\u0e32\u0e19\u0e2d\u0e31\u0e19\u0e42\u0e15\u0e19\u0e34\u0e42\u0e2d\u0e40\u0e14\u0e1b\u0e32\u0e40\u0e25"
    ],
    "name:tur_x_preferred":[
        "San Antonio de Pal\u00e9"
    ],
    "name:ukr_x_preferred":[
        "\u0421\u0430\u043d-\u0410\u043d\u0442\u043e\u043d\u0456\u043e-\u0434\u0435-\u041f\u0430\u043b\u0435"
    ],
    "name:und_x_variant":[
        "San Antonio"
    ],
    "qs:gn_country":"GQ",
    "qs:gn_fcode":"PPLA",
    "qs:gn_pop":4433,
    "qs:name":"Pal\u00e9",
    "qs:name_adm0":"Guinea Ecuatorial",
    "qs:name_adm1":"Annobon",
    "qs:photos":0,
    "qs:photos_1k":0,
    "qs:photos_9k":1,
    "qs:photos_9r":1,
    "qs:photos_all":1,
    "qs:photos_sr":0,
    "qs:placetype":"Town",
    "qs:pop_sr":"4",
    "qs:woe_adm0":23424804,
    "wof:name":"Pal\u00e9",
    "wof:placetype":"locality",
    "wof:population":4433
},
  "geometry": {"coordinates":[5.6325,-1.40139],"type":"Point"}
}