{
  "type": "Feature",
  "properties": {
    "gn:admin1_code":"00",
    "gn:asciiname":"Acaasi",
    "gn:country_code":"GQ",
    "gn:dem":673,
    "gn:feature_class":"P",
    "gn:feature_code":"PPL",
    "gn:name":"Acaasi",
    "gn:population":0,
    "gn:timezone":"Africa/Malabo",
    "iso:country":"GQ",
    "name:und_x_variant":[
        "Aka\u2019asi",
        "Acaasi"
    ],
    "wof:name":"Acaasi",
    "wof:placetype":"locality"
},
  "geometry": {"coordinates":[11.2821,1.55161],"type":"Point"}
}