{
  "type": "Feature",
  "properties": {
    "gn:admin1_code":"00",
    "gn:asciiname":"Cogo",
    "gn:country_code":"GQ",
    "gn:dem":4,
    "gn:feature_class":"P",
    "gn:feature_code":"PPL",
    "gn:name":"Cogo",
    "gn:population":0,
    "gn:timezone":"Africa/Malabo",
    "iso:country":"GQ",
    "name:und_x_variant":[
        "Puerto Iradier",
        "Koga",
        "Kogo",
        "Cogo"
    ],
    "wof:name":"Cogo",
    "wof:placetype":"locality"
},
  "geometry": {"coordinates":[9.693,1.08425],"type":"Point"}
}