{
  "type": "Feature",
  "properties": {
    "gn:admin1_code":"00",
    "gn:asciiname":"Mocomo",
    "gn:country_code":"GQ",
    "gn:dem":533,
    "gn:feature_class":"P",
    "gn:feature_code":"PPL",
    "gn:name":"Mocomo",
    "gn:population":0,
    "gn:timezone":"Africa/Malabo",
    "iso:country":"GQ",
    "name:und_x_variant":[
        "Mokomo",
        "Mocomo"
    ],
    "wof:name":"Mocomo",
    "wof:placetype":"locality"
},
  "geometry": {"coordinates":[10.82682,1.73961],"type":"Point"}
}