{
  "type": "Feature",
  "properties": {
    "gn:admin1_code":"00",
    "gn:asciiname":"Ulato",
    "gn:country_code":"GQ",
    "gn:dem":19,
    "gn:feature_class":"P",
    "gn:feature_code":"PPL",
    "gn:name":"Ulato",
    "gn:population":0,
    "gn:timezone":"Africa/Malabo",
    "iso:country":"GQ",
    "wof:name":"Ulato",
    "wof:placetype":"locality"
},
  "geometry": {"coordinates":[9.31898,0.89419],"type":"Point"}
}