{
  "type": "Feature",
  "properties": {
    "gn:admin1_code":"00",
    "gn:asciiname":"Bedubu",
    "gn:country_code":"GQ",
    "gn:dem":-9999,
    "gn:feature_class":"P",
    "gn:feature_code":"PPL",
    "gn:name":"Bedubu",
    "gn:population":0,
    "gn:timezone":"Africa/Malabo",
    "iso:country":"GQ",
    "name:und_x_variant":[
        "Bebudu",
        "Beduba",
        "Bedubu"
    ],
    "wof:name":"Bedubu",
    "wof:placetype":"locality"
},
  "geometry": {"coordinates":[9.30504,0.91795],"type":"Point"}
}