{
  "type": "Feature",
  "properties": {
    "gn:admin1_code":"00",
    "gn:asciiname":"Mongola",
    "gn:country_code":"GQ",
    "gn:dem":662,
    "gn:feature_class":"P",
    "gn:feature_code":"PPL",
    "gn:name":"Mongola",
    "gn:population":0,
    "gn:timezone":"Africa/Malabo",
    "iso:country":"GQ",
    "name:und_x_variant":[
        "Mangola",
        "Mongola"
    ],
    "wof:name":"Mongola",
    "wof:placetype":"locality"
},
  "geometry": {"coordinates":[10.53128,1.52141],"type":"Point"}
}