{
  "type": "Feature",
  "properties": {
    "gn:admin1_code":"00",
    "gn:asciiname":"Ayanesala",
    "gn:country_code":"GQ",
    "gn:dem":134,
    "gn:feature_class":"P",
    "gn:feature_code":"PPL",
    "gn:name":"Ayanesala",
    "gn:population":0,
    "gn:timezone":"Africa/Malabo",
    "iso:country":"GQ",
    "name:und_x_variant":[
        "Ayenesala",
        "Ayanesala"
    ],
    "wof:name":"Ayanesala",
    "wof:placetype":"locality"
},
  "geometry": {"coordinates":[9.93881,1.19878],"type":"Point"}
}