{
  "type": "Feature",
  "properties": {
    "gn:admin1_code":"00",
    "gn:asciiname":"Melen",
    "gn:country_code":"GQ",
    "gn:dem":616,
    "gn:feature_class":"P",
    "gn:feature_code":"PPL",
    "gn:name":"Melen",
    "gn:population":0,
    "gn:timezone":"Africa/Malabo",
    "iso:country":"GQ",
    "wof:name":"Melen",
    "wof:placetype":"locality"
},
  "geometry": {"coordinates":[11.28333,2.06667],"type":"Point"}
}