{
  "type": "Feature",
  "properties": {
    "gn:admin1_code":"00",
    "gn:asciiname":"Acocnfang",
    "gn:country_code":"GQ",
    "gn:dem":224,
    "gn:feature_class":"P",
    "gn:feature_code":"PPL",
    "gn:name":"Acocnfang",
    "gn:population":0,
    "gn:timezone":"Africa/Malabo",
    "iso:country":"GQ",
    "name:und_x_variant":[
        "Akokufang",
        "Acocnfang"
    ],
    "wof:name":"Acocnfang",
    "wof:placetype":"locality"
},
  "geometry": {"coordinates":[9.96248,1.76842],"type":"Point"}
}