{
  "type": "Feature",
  "properties": {
    "gn:admin1_code":"00",
    "gn:asciiname":"Niefala",
    "gn:country_code":"GQ",
    "gn:dem":19,
    "gn:feature_class":"P",
    "gn:feature_code":"PPL",
    "gn:name":"Niefala",
    "gn:population":0,
    "gn:timezone":"Africa/Malabo",
    "iso:country":"GQ",
    "name:und_x_variant":[
        "Nniefala",
        "Niefala"
    ],
    "wof:name":"Niefala",
    "wof:placetype":"locality"
},
  "geometry": {"coordinates":[10.01347,0.9688],"type":"Point"}
}