{
  "type": "Feature",
  "properties": {
    "gn:admin1_code":"00",
    "gn:asciiname":"Ayaantang",
    "gn:country_code":"GQ",
    "gn:dem":346,
    "gn:feature_class":"P",
    "gn:feature_code":"PPL",
    "gn:name":"Ayaantang",
    "gn:population":0,
    "gn:timezone":"Africa/Malabo",
    "iso:country":"GQ",
    "name:und_x_variant":[
        "Aya\u2018ntang",
        "Ayaantang"
    ],
    "wof:name":"Ayaantang",
    "wof:placetype":"locality"
},
  "geometry": {"coordinates":[10.39359,1.95985],"type":"Point"}
}