{
  "type": "Feature",
  "properties": {
    "gn:admin1_code":"00",
    "gn:asciiname":"Ndangueng",
    "gn:country_code":"GQ",
    "gn:dem":643,
    "gn:feature_class":"P",
    "gn:feature_code":"PPL",
    "gn:name":"Ndangueng",
    "gn:population":0,
    "gn:timezone":"Africa/Malabo",
    "iso:country":"GQ",
    "wof:name":"Ndangueng",
    "wof:placetype":"locality"
},
  "geometry": {"coordinates":[11.36313,1.82883],"type":"Point"}
}