{
  "type": "Feature",
  "properties": {
    "gn:admin1_code":"00",
    "gn:asciiname":"Mendung",
    "gn:country_code":"GQ",
    "gn:dem":593,
    "gn:feature_class":"P",
    "gn:feature_code":"PPL",
    "gn:name":"Mendung",
    "gn:population":0,
    "gn:timezone":"Africa/Malabo",
    "iso:country":"GQ",
    "wof:name":"Mendung",
    "wof:placetype":"locality"
},
  "geometry": {"coordinates":[10.41954,1.71918],"type":"Point"}
}