{
  "type": "Feature",
  "properties": {
    "gn:admin1_code":"00",
    "gn:asciiname":"Com",
    "gn:country_code":"GQ",
    "gn:dem":661,
    "gn:feature_class":"P",
    "gn:feature_code":"PPL",
    "gn:name":"Com",
    "gn:population":0,
    "gn:timezone":"Africa/Malabo",
    "iso:country":"GQ",
    "name:fin_x_preferred":[
        "Com"
    ],
    "name:hun_x_preferred":[
        "COM"
    ],
    "name:ron_x_preferred":[
        "Com"
    ],
    "name:tur_x_preferred":[
        "Com"
    ],
    "wof:name":"Com",
    "wof:placetype":"locality"
},
  "geometry": {"coordinates":[11.25526,1.49263],"type":"Point"}
}