{
  "type": "Feature",
  "properties": {
    "gn:admin1_code":"00",
    "gn:asciiname":"Ntoayop",
    "gn:country_code":"GQ",
    "gn:dem":670,
    "gn:feature_class":"P",
    "gn:feature_code":"PPL",
    "gn:name":"Ntoayop",
    "gn:population":0,
    "gn:timezone":"Africa/Malabo",
    "iso:country":"GQ",
    "wof:name":"Ntoayop",
    "wof:placetype":"locality"
},
  "geometry": {"coordinates":[11.29097,1.40078],"type":"Point"}
}