{
  "type": "Feature",
  "properties": {
    "gn:admin1_code":"00",
    "gn:asciiname":"Nlosoc",
    "gn:country_code":"GQ",
    "gn:dem":34,
    "gn:feature_class":"P",
    "gn:feature_code":"PPL",
    "gn:name":"Nlosoc",
    "gn:population":0,
    "gn:timezone":"Africa/Malabo",
    "iso:country":"GQ",
    "name:und_x_variant":[
        "Nlonsok",
        "Nlosoc"
    ],
    "wof:name":"Nlosoc",
    "wof:placetype":"locality"
},
  "geometry": {"coordinates":[9.80932,2.08304],"type":"Point"}
}