{
  "type": "Feature",
  "properties": {
    "gn:admin1_code":"00",
    "gn:asciiname":"Oveng",
    "gn:country_code":"GQ",
    "gn:dem":642,
    "gn:feature_class":"P",
    "gn:feature_code":"PPL",
    "gn:name":"Oveng",
    "gn:population":0,
    "gn:timezone":"Africa/Malabo",
    "iso:country":"GQ",
    "wof:name":"Oveng",
    "wof:placetype":"locality"
},
  "geometry": {"coordinates":[10.48466,1.46955],"type":"Point"}
}