{
  "type": "Feature",
  "properties": {
    "gn:admin1_code":"00",
    "gn:asciiname":"Ecumongom",
    "gn:country_code":"GQ",
    "gn:dem":39,
    "gn:feature_class":"P",
    "gn:feature_code":"PPL",
    "gn:name":"Ecumongom",
    "gn:population":0,
    "gn:timezone":"Africa/Malabo",
    "iso:country":"GQ",
    "wof:name":"Ecumongom",
    "wof:placetype":"locality"
},
  "geometry": {"coordinates":[9.6071,1.33849],"type":"Point"}
}