{
  "type": "Feature",
  "properties": {
    "gn:admin1_code":"00",
    "gn:asciiname":"Ncoaecuc",
    "gn:country_code":"GQ",
    "gn:dem":206,
    "gn:feature_class":"P",
    "gn:feature_code":"PPL",
    "gn:name":"Ncoaecuc",
    "gn:population":0,
    "gn:timezone":"Africa/Malabo",
    "iso:country":"GQ",
    "name:und_x_variant":[
        "Nko\u2019ekuk",
        "Ncoaecuc"
    ],
    "wof:name":"Ncoaecuc",
    "wof:placetype":"locality"
},
  "geometry": {"coordinates":[9.97471,1.93182],"type":"Point"}
}