{
  "type": "Feature",
  "properties": {
    "gn:admin1_code":"00",
    "gn:asciiname":"Olop",
    "gn:country_code":"GQ",
    "gn:dem":27,
    "gn:feature_class":"P",
    "gn:feature_code":"PPL",
    "gn:name":"Olop",
    "gn:population":0,
    "gn:timezone":"Africa/Malabo",
    "iso:country":"GQ",
    "wof:name":"Olop",
    "wof:placetype":"locality"
},
  "geometry": {"coordinates":[9.5617,1.14594],"type":"Point"}
}