{
  "type": "Feature",
  "properties": {
    "gn:admin1_code":"00",
    "gn:asciiname":"Iguene",
    "gn:country_code":"GQ",
    "gn:dem":29,
    "gn:feature_class":"P",
    "gn:feature_code":"PPL",
    "gn:name":"Iguene",
    "gn:population":0,
    "gn:timezone":"Africa/Malabo",
    "iso:country":"GQ",
    "wof:name":"Iguene",
    "wof:placetype":"locality"
},
  "geometry": {"coordinates":[9.46956,1.37351],"type":"Point"}
}