{
  "type": "Feature",
  "properties": {
    "gn:admin1_code":"00",
    "gn:asciiname":"Mayala",
    "gn:country_code":"GQ",
    "gn:dem":656,
    "gn:feature_class":"P",
    "gn:feature_code":"PPL",
    "gn:name":"Mayala",
    "gn:population":0,
    "gn:timezone":"Africa/Malabo",
    "iso:country":"GQ",
    "wof:name":"Mayala",
    "wof:placetype":"locality"
},
  "geometry": {"coordinates":[10.37431,1.90448],"type":"Point"}
}