{
  "type": "Feature",
  "properties": {
    "gn:country":"GQ",
    "gn:fcode":"PPL",
    "gn:pop":5813,
    "iso:country":"GQ",
    "name:bul_x_preferred":[
        "\u041c\u0438\u043a\u043e\u043c\u0435\u0441\u0435\u043d\u0433"
    ],
    "name:cat_x_preferred":[
        "Micomeseng"
    ],
    "name:eng_x_preferred":[
        "Micomeseng"
    ],
    "name:fra_x_preferred":[
        "Mikomeseng"
    ],
    "name:ind_x_preferred":[
        "Mikomeseng"
    ],
    "name:ita_x_preferred":[
        "Micomeseng"
    ],
    "name:nld_x_preferred":[
        "Micomeseng"
    ],
    "name:pol_x_preferred":[
        "Mikomeseng"
    ],
    "name:por_x_preferred":[
        "Micomeseng"
    ],
    "name:spa_x_preferred":[
        "Micomeseng"
    ],
    "name:swe_x_preferred":[
        "Mikomeseng"
    ],
    "name:tgl_x_preferred":[
        "Micomeseng"
    ],
    "name:tur_x_preferred":[
        "Micomeseng"
    ],
    "name:unk_x_variant":[
        "Micomeseng"
    ],
    "name:zho_x_preferred":[
        "\u7c73\u79d1\u6885\u68ee"
    ],
    "qs:name":"Mikomeseng",
    "qs:photos_9r":0,
    "qs:photos_sr":0,
    "qs:pop_sr":"5",
    "wof:name":"Mikomeseng",
    "wof:placetype":"locality",
    "wof:population":5813
},
  "geometry": {"coordinates":[10.61322,2.13609],"type":"Point"}
}