{
  "type": "Feature",
  "properties": {
    "gn:admin1_code":"00",
    "gn:asciiname":"Ilale",
    "gn:country_code":"GQ",
    "gn:dem":9,
    "gn:feature_class":"P",
    "gn:feature_code":"PPL",
    "gn:name":"Ilale",
    "gn:population":0,
    "gn:timezone":"Africa/Malabo",
    "iso:country":"GQ",
    "name:und_x_variant":[
        "Ilale-Igene",
        "Ilale"
    ],
    "wof:name":"Ilale",
    "wof:placetype":"locality"
},
  "geometry": {"coordinates":[9.52326,1.44584],"type":"Point"}
}