{
  "type": "Feature",
  "properties": {
    "gn:admin1_code":"00",
    "gn:asciiname":"Nbubui",
    "gn:country_code":"GQ",
    "gn:dem":333,
    "gn:feature_class":"P",
    "gn:feature_code":"PPL",
    "gn:name":"Nbubui",
    "gn:population":0,
    "gn:timezone":"Africa/Malabo",
    "iso:country":"GQ",
    "wof:name":"Nbubui",
    "wof:placetype":"locality"
},
  "geometry": {"coordinates":[10.26894,1.87266],"type":"Point"}
}