{
  "type": "Feature",
  "properties": {
    "gn:admin1_code":"00",
    "gn:asciiname":"Ecuc",
    "gn:country_code":"GQ",
    "gn:dem":37,
    "gn:feature_class":"P",
    "gn:feature_code":"PPL",
    "gn:name":"Ecuc",
    "gn:population":0,
    "gn:timezone":"Africa/Malabo",
    "iso:country":"GQ",
    "wof:name":"Ecuc",
    "wof:placetype":"locality"
},
  "geometry": {"coordinates":[9.73573,1.47894],"type":"Point"}
}