{
  "type": "Feature",
  "properties": {
    "gn:admin1_code":"00",
    "gn:asciiname":"Aban",
    "gn:country_code":"GQ",
    "gn:dem":540,
    "gn:feature_class":"P",
    "gn:feature_code":"PPL",
    "gn:name":"Aban",
    "gn:population":0,
    "gn:timezone":"Africa/Malabo",
    "iso:country":"GQ",
    "name:fas_x_preferred":[
        "\u0622\u0628\u0627\u0646\u06af\u0627\u0646"
    ],
    "name:jpn_x_preferred":[
        "\u30a2\u30fc\u30d7"
    ],
    "name:und_x_variant":[
        "Abam",
        "Aban"
    ],
    "wof:name":"Aban",
    "wof:placetype":"locality"
},
  "geometry": {"coordinates":[10.86364,1.83974],"type":"Point"}
}