{
  "type": "Feature",
  "properties": {
    "gn:admin1_code":"00",
    "gn:asciiname":"Dumanduin",
    "gn:country_code":"GQ",
    "gn:dem":594,
    "gn:feature_class":"P",
    "gn:feature_code":"PPL",
    "gn:name":"Dumanduin",
    "gn:population":0,
    "gn:timezone":"Africa/Malabo",
    "iso:country":"GQ",
    "wof:name":"Dumanduin",
    "wof:placetype":"locality"
},
  "geometry": {"coordinates":[11.05,2.08333],"type":"Point"}
}