{
  "type": "Feature",
  "properties": {
    "gn:admin1_code":"00",
    "gn:asciiname":"Zaragoza",
    "gn:country_code":"GQ",
    "gn:dem":58,
    "gn:feature_class":"P",
    "gn:feature_code":"PPL",
    "gn:name":"Zaragoza",
    "gn:population":0,
    "gn:timezone":"Africa/Malabo",
    "iso:country":"GQ",
    "wof:name":"Zaragoza",
    "wof:placetype":"locality"
},
  "geometry": {"coordinates":[9.84892,1.19863],"type":"Point"}
}