{
  "type": "Feature",
  "properties": {
    "gn:admin1_code":"00",
    "gn:asciiname":"Cotango",
    "gn:country_code":"GQ",
    "gn:dem":-9999,
    "gn:feature_class":"P",
    "gn:feature_code":"PPL",
    "gn:name":"Cotango",
    "gn:population":0,
    "gn:timezone":"Africa/Malabo",
    "iso:country":"GQ",
    "wof:name":"Cotango",
    "wof:placetype":"locality"
},
  "geometry": {"coordinates":[9.58716,1.55167],"type":"Point"}
}