{
  "type": "Feature",
  "properties": {
    "gn:admin1_code":"00",
    "gn:asciiname":"Eyen",
    "gn:country_code":"GQ",
    "gn:dem":626,
    "gn:feature_class":"P",
    "gn:feature_code":"PPL",
    "gn:name":"Eyen",
    "gn:population":0,
    "gn:timezone":"Africa/Malabo",
    "iso:country":"GQ",
    "name:und_x_variant":[
        "Ayuen",
        "Eyen"
    ],
    "wof:name":"Eyen",
    "wof:placetype":"locality"
},
  "geometry": {"coordinates":[11.0601,2.0382],"type":"Point"}
}