{
  "type": "Feature",
  "properties": {
    "gn:admin1_code":"00",
    "gn:asciiname":"Macomo",
    "gn:country_code":"GQ",
    "gn:dem":625,
    "gn:feature_class":"P",
    "gn:feature_code":"PPL",
    "gn:name":"Macomo",
    "gn:population":0,
    "gn:timezone":"Africa/Malabo",
    "iso:country":"GQ",
    "name:und_x_variant":[
        "Makomo",
        "Macomo"
    ],
    "wof:name":"Macomo",
    "wof:placetype":"locality"
},
  "geometry": {"coordinates":[11.25398,2.0476],"type":"Point"}
}