{
  "type": "Feature",
  "properties": {
    "gn:admin1_code":"00",
    "gn:asciiname":"Acoc",
    "gn:country_code":"GQ",
    "gn:dem":610,
    "gn:feature_class":"P",
    "gn:feature_code":"PPL",
    "gn:name":"Acoc",
    "gn:population":0,
    "gn:timezone":"Africa/Malabo",
    "iso:country":"GQ",
    "name:und_x_variant":[
        "Akok",
        "Acoc"
    ],
    "wof:name":"Acoc",
    "wof:placetype":"locality"
},
  "geometry": {"coordinates":[10.44027,1.13212],"type":"Point"}
}