{
  "type": "Feature",
  "properties": {
    "gn:admin1_code":"00",
    "gn:asciiname":"Ncoaekie",
    "gn:country_code":"GQ",
    "gn:dem":26,
    "gn:feature_class":"P",
    "gn:feature_code":"PPL",
    "gn:name":"Ncoaeki\u00e9",
    "gn:population":0,
    "gn:timezone":"Africa/Malabo",
    "iso:country":"GQ",
    "wof:name":"Ncoaekie",
    "wof:placetype":"locality"
},
  "geometry": {"coordinates":[9.80042,1.71314],"type":"Point"}
}