{
  "type": "Feature",
  "properties": {
    "gn:admin1_code":"00",
    "gn:asciiname":"Metolo",
    "gn:country_code":"GQ",
    "gn:dem":23,
    "gn:feature_class":"P",
    "gn:feature_code":"PPL",
    "gn:name":"Metolo",
    "gn:population":0,
    "gn:timezone":"Africa/Malabo",
    "iso:country":"GQ",
    "wof:name":"Metolo",
    "wof:placetype":"locality"
},
  "geometry": {"coordinates":[9.31887,0.89501],"type":"Point"}
}