{
  "type": "Feature",
  "properties": {
    "gn:admin1_code":"00",
    "gn:asciiname":"Egon",
    "gn:country_code":"GQ",
    "gn:dem":597,
    "gn:feature_class":"P",
    "gn:feature_code":"PPL",
    "gn:name":"Egon",
    "gn:population":0,
    "gn:timezone":"Africa/Malabo",
    "iso:country":"GQ",
    "name:und_x_variant":[
        "Eguong-Niemayong",
        "Egon"
    ],
    "wof:name":"Egon",
    "wof:placetype":"locality"
},
  "geometry": {"coordinates":[10.9357,2.13675],"type":"Point"}
}