{
  "type": "Feature",
  "properties": {
    "gn:admin1_code":"00",
    "gn:asciiname":"Mabuki",
    "gn:country_code":"GQ",
    "gn:dem":14,
    "gn:feature_class":"P",
    "gn:feature_code":"PPL",
    "gn:name":"Mabuki",
    "gn:population":0,
    "gn:timezone":"Africa/Malabo",
    "iso:country":"GQ",
    "wof:name":"Mabuki",
    "wof:placetype":"locality"
},
  "geometry": {"coordinates":[9.37389,1.19559],"type":"Point"}
}