{
  "type": "Feature",
  "properties": {
    "gn:admin1_code":"00",
    "gn:asciiname":"Mefeng",
    "gn:country_code":"GQ",
    "gn:dem":585,
    "gn:feature_class":"P",
    "gn:feature_code":"PPL",
    "gn:name":"Mefeng",
    "gn:population":0,
    "gn:timezone":"Africa/Malabo",
    "iso:country":"GQ",
    "wof:name":"Mefeng",
    "wof:placetype":"locality"
},
  "geometry": {"coordinates":[11.30443,2.11495],"type":"Point"}
}