{
  "type": "Feature",
  "properties": {
    "gn:admin1_code":"00",
    "gn:asciiname":"Noayong",
    "gn:country_code":"GQ",
    "gn:dem":37,
    "gn:feature_class":"P",
    "gn:feature_code":"PPL",
    "gn:name":"Noayong",
    "gn:population":0,
    "gn:timezone":"Africa/Malabo",
    "iso:country":"GQ",
    "name:und_x_variant":[
        "Nnoayong",
        "Nuoayong",
        "Noayong"
    ],
    "wof:name":"Noayong",
    "wof:placetype":"locality"
},
  "geometry": {"coordinates":[9.83326,1.1589],"type":"Point"}
}