{
  "type": "Feature",
  "properties": {
    "gn:admin1_code":"00",
    "gn:asciiname":"Bileng",
    "gn:country_code":"GQ",
    "gn:dem":212,
    "gn:feature_class":"P",
    "gn:feature_code":"PPL",
    "gn:name":"Bileng",
    "gn:population":0,
    "gn:timezone":"Africa/Malabo",
    "iso:country":"GQ",
    "wof:name":"Bileng",
    "wof:placetype":"locality"
},
  "geometry": {"coordinates":[10.03106,1.85455],"type":"Point"}
}