{
  "type": "Feature",
  "properties": {
    "gn:admin1_code":"00",
    "gn:asciiname":"Temelon",
    "gn:country_code":"GQ",
    "gn:dem":435,
    "gn:feature_class":"P",
    "gn:feature_code":"PPL",
    "gn:name":"Temel\u00f3n",
    "gn:population":0,
    "gn:timezone":"Africa/Malabo",
    "iso:country":"GQ",
    "wof:name":"Temelon",
    "wof:placetype":"locality"
},
  "geometry": {"coordinates":[10.62671,1.9269],"type":"Point"}
}