{
  "type": "Feature",
  "properties": {
    "gn:admin1_code":"00",
    "gn:asciiname":"Nbona",
    "gn:country_code":"GQ",
    "gn:dem":405,
    "gn:feature_class":"P",
    "gn:feature_code":"PPL",
    "gn:name":"Nbona",
    "gn:population":0,
    "gn:timezone":"Africa/Malabo",
    "iso:country":"GQ",
    "wof:name":"Nbona",
    "wof:placetype":"locality"
},
  "geometry": {"coordinates":[10.41722,2.07961],"type":"Point"}
}