{
  "type": "Feature",
  "properties": {
    "gn:admin1_code":"00",
    "gn:asciiname":"Echam",
    "gn:country_code":"GQ",
    "gn:dem":563,
    "gn:feature_class":"P",
    "gn:feature_code":"PPL",
    "gn:name":"Echam",
    "gn:population":0,
    "gn:timezone":"Africa/Malabo",
    "iso:country":"GQ",
    "wof:name":"Echam",
    "wof:placetype":"locality"
},
  "geometry": {"coordinates":[10.24445,1.02222],"type":"Point"}
}