{
  "type": "Feature",
  "properties": {
    "gn:admin1_code":"00",
    "gn:asciiname":"Oveng",
    "gn:country_code":"GQ",
    "gn:dem":651,
    "gn:feature_class":"P",
    "gn:feature_code":"PPL",
    "gn:name":"Oveng",
    "gn:population":0,
    "gn:timezone":"Africa/Malabo",
    "iso:country":"GQ",
    "wof:name":"Oveng",
    "wof:placetype":"locality"
},
  "geometry": {"coordinates":[11.19023,1.55098],"type":"Point"}
}