{
  "type": "Feature",
  "properties": {
    "gn:admin1_code":"00",
    "gn:asciiname":"Acoacan",
    "gn:country_code":"GQ",
    "gn:dem":671,
    "gn:feature_class":"P",
    "gn:feature_code":"PPL",
    "gn:name":"Acoacan",
    "gn:population":0,
    "gn:timezone":"Africa/Malabo",
    "iso:country":"GQ",
    "name:und_x_variant":[
        "Acoacam",
        "Akokam",
        "Acoacan"
    ],
    "wof:name":"Acoacan",
    "wof:placetype":"locality"
},
  "geometry": {"coordinates":[11.30741,1.60994],"type":"Point"}
}