{
  "type": "Feature",
  "properties": {
    "gn:admin1_code":"00",
    "gn:asciiname":"Acoacan",
    "gn:country_code":"GQ",
    "gn:dem":671,
    "gn:feature_class":"P",
    "gn:feature_code":"PPL",
    "gn:name":"Acoacan",
    "gn:population":0,
    "gn:timezone":"Africa/Malabo",
    "iso:country":"GQ",
    "name:fas_x_preferred":[
        "\u0627\u06a9\u0648\u0627\u06a9\u0627\u0646"
    ],
    "name:lit_x_preferred":[
        "Akoakanas"
    ],
    "name:por_x_preferred":[
        "Acoac\u00e1n"
    ],
    "name:sco_x_preferred":[
        "Acoac\u00e1n"
    ],
    "name:spa_x_preferred":[
        "Acoac\u00e1n"
    ],
    "name:und_x_variant":[
        "Acoacam",
        "Akokam",
        "Acoacan"
    ],
    "wof:name":"Acoacan",
    "wof:placetype":"locality"
},
  "geometry": {"coordinates":[11.30741,1.60994],"type":"Point"}
}