{
  "type": "Feature",
  "properties": {
    "gn:admin1_code":"00",
    "gn:asciiname":"Ibonga",
    "gn:country_code":"GQ",
    "gn:dem":16,
    "gn:feature_class":"P",
    "gn:feature_code":"PPL",
    "gn:name":"Ibonga",
    "gn:population":0,
    "gn:timezone":"Africa/Malabo",
    "iso:country":"GQ",
    "wof:name":"Ibonga",
    "wof:placetype":"locality"
},
  "geometry": {"coordinates":[9.32688,0.93239],"type":"Point"}
}