{
  "type": "Feature",
  "properties": {
    "gn:admin1_code":"00",
    "gn:asciiname":"Evinayong",
    "gn:country_code":"GQ",
    "gn:dem":519,
    "gn:feature_class":"P",
    "gn:feature_code":"PPL",
    "gn:name":"Evinayong",
    "gn:population":0,
    "gn:timezone":"Africa/Malabo",
    "iso:country":"GQ",
    "wof:name":"Evinayong",
    "wof:placetype":"locality"
},
  "geometry": {"coordinates":[10.61488,1.73891],"type":"Point"}
}