{
  "type": "Feature",
  "properties": {
    "gn:admin1_code":"00",
    "gn:asciiname":"Mandoc",
    "gn:country_code":"GQ",
    "gn:dem":424,
    "gn:feature_class":"P",
    "gn:feature_code":"PPL",
    "gn:name":"Mandoc",
    "gn:population":0,
    "gn:timezone":"Africa/Malabo",
    "iso:country":"GQ",
    "name:und_x_variant":[
        "Mandok",
        "Mandoc"
    ],
    "wof:name":"Mandoc",
    "wof:placetype":"locality"
},
  "geometry": {"coordinates":[10.49697,1.93774],"type":"Point"}
}