{
  "type": "Feature",
  "properties": {
    "gn:admin1_code":"00",
    "gn:asciiname":"Micomibe",
    "gn:country_code":"GQ",
    "gn:dem":30,
    "gn:feature_class":"P",
    "gn:feature_code":"PPL",
    "gn:name":"Micomibe",
    "gn:population":0,
    "gn:timezone":"Africa/Malabo",
    "iso:country":"GQ",
    "name:und_x_variant":[
        "Mikomibe",
        "Micomibe"
    ],
    "wof:name":"Micomibe",
    "wof:placetype":"locality"
},
  "geometry": {"coordinates":[9.71582,1.66295],"type":"Point"}
}