{
  "type": "Feature",
  "properties": {
    "gn:admin1_code":"00",
    "gn:asciiname":"Nsuemam",
    "gn:country_code":"GQ",
    "gn:dem":138,
    "gn:feature_class":"P",
    "gn:feature_code":"PPL",
    "gn:name":"Nsuemam",
    "gn:population":0,
    "gn:timezone":"Africa/Malabo",
    "iso:country":"GQ",
    "wof:name":"Nsuemam",
    "wof:placetype":"locality"
},
  "geometry": {"coordinates":[9.97243,1.9562],"type":"Point"}
}