{
  "type": "Feature",
  "properties": {
    "gn:admin1_code":"00",
    "gn:asciiname":"Nsem",
    "gn:country_code":"GQ",
    "gn:dem":628,
    "gn:feature_class":"P",
    "gn:feature_code":"PPL",
    "gn:name":"Nsem",
    "gn:population":0,
    "gn:timezone":"Africa/Malabo",
    "iso:country":"GQ",
    "name:deu_x_preferred":[
        "Nsem"
    ],
    "name:fra_x_preferred":[
        "Nsem"
    ],
    "name:ita_x_preferred":[
        "Nsem"
    ],
    "name:msa_x_preferred":[
        "Nsem"
    ],
    "name:spa_x_preferred":[
        "Nsem"
    ],
    "wof:name":"Nsem",
    "wof:placetype":"locality"
},
  "geometry": {"coordinates":[10.57321,1.30548],"type":"Point"}
}