{
  "type": "Feature",
  "properties": {
    "gn:admin1_code":"00",
    "gn:asciiname":"Bantabare Pequeno",
    "gn:country_code":"GQ",
    "gn:dem":253,
    "gn:feature_class":"P",
    "gn:feature_code":"PPL",
    "gn:name":"Bantabar\u00e9 Peque\u00f1o",
    "gn:population":0,
    "gn:timezone":"Africa/Malabo",
    "iso:country":"GQ",
    "wof:name":"Bantabare Pequeno",
    "wof:placetype":"locality"
},
  "geometry": {"coordinates":[8.77973,3.45538],"type":"Point"}
}