{
  "type": "Feature",
  "properties": {
    "gn:admin1_code":"00",
    "gn:asciiname":"Binguru",
    "gn:country_code":"GQ",
    "gn:dem":50,
    "gn:feature_class":"P",
    "gn:feature_code":"PPL",
    "gn:name":"Binguru",
    "gn:population":0,
    "gn:timezone":"Africa/Malabo",
    "iso:country":"GQ",
    "wof:name":"Binguru",
    "wof:placetype":"locality"
},
  "geometry": {"coordinates":[9.80446,1.50243],"type":"Point"}
}