{
  "type": "Feature",
  "properties": {
    "gn:admin1_code":"00",
    "gn:asciiname":"Namicale",
    "gn:country_code":"GQ",
    "gn:dem":27,
    "gn:feature_class":"P",
    "gn:feature_code":"PPL",
    "gn:name":"\u00d1amicale",
    "gn:population":0,
    "gn:timezone":"Africa/Malabo",
    "iso:country":"GQ",
    "wof:name":"Namicale",
    "wof:placetype":"locality"
},
  "geometry": {"coordinates":[9.73684,1.61295],"type":"Point"}
}