{
  "type": "Feature",
  "properties": {
    "gn:admin1_code":"00",
    "gn:asciiname":"Alon",
    "gn:country_code":"GQ",
    "gn:dem":570,
    "gn:feature_class":"P",
    "gn:feature_code":"PPL",
    "gn:name":"Alon",
    "gn:population":0,
    "gn:timezone":"Africa/Malabo",
    "iso:country":"GQ",
    "name:ceb_x_preferred":[
        "Alon"
    ],
    "name:ces_x_preferred":[
        "Alon"
    ],
    "name:deu_x_preferred":[
        "Alon"
    ],
    "name:fra_x_preferred":[
        "Alon"
    ],
    "name:heb_x_preferred":[
        "\u05d0\u05dc\u05d5\u05df"
    ],
    "name:slv_x_preferred":[
        "Alon"
    ],
    "name:swe_x_preferred":[
        "Alon"
    ],
    "wof:name":"Alon",
    "wof:placetype":"locality"
},
  "geometry": {"coordinates":[11.31038,2.07036],"type":"Point"}
}