{
  "type": "Feature",
  "properties": {
    "gn:admin1_code":"00",
    "gn:asciiname":"Alon",
    "gn:country_code":"GQ",
    "gn:dem":570,
    "gn:feature_class":"P",
    "gn:feature_code":"PPL",
    "gn:name":"Alon",
    "gn:population":0,
    "gn:timezone":"Africa/Malabo",
    "iso:country":"GQ",
    "wof:name":"Alon",
    "wof:placetype":"locality"
},
  "geometry": {"coordinates":[11.31038,2.07036],"type":"Point"}
}