{
  "type": "Feature",
  "properties": {
    "gn:admin1_code":"00",
    "gn:asciiname":"Midyobo",
    "gn:country_code":"GQ",
    "gn:dem":842,
    "gn:feature_class":"P",
    "gn:feature_code":"PPL",
    "gn:name":"Midyobo",
    "gn:population":0,
    "gn:timezone":"Africa/Malabo",
    "iso:country":"GQ",
    "wof:name":"Midyobo",
    "wof:placetype":"locality"
},
  "geometry": {"coordinates":[10.52713,1.38118],"type":"Point"}
}