{
  "type": "Feature",
  "properties": {
    "gn:admin1_code":"00",
    "gn:asciiname":"Evuennan",
    "gn:country_code":"GQ",
    "gn:dem":486,
    "gn:feature_class":"P",
    "gn:feature_code":"PPL",
    "gn:name":"Evuennan",
    "gn:population":0,
    "gn:timezone":"Africa/Malabo",
    "iso:country":"GQ",
    "name:und_x_variant":[
        "Evueman",
        "Evuennan"
    ],
    "wof:name":"Evuennan",
    "wof:placetype":"locality"
},
  "geometry": {"coordinates":[10.60331,1.77791],"type":"Point"}
}