{
  "type": "Feature",
  "properties": {
    "gn:admin1_code":"00",
    "gn:asciiname":"Acombele",
    "gn:country_code":"GQ",
    "gn:dem":463,
    "gn:feature_class":"P",
    "gn:feature_code":"PPL",
    "gn:name":"Acombele",
    "gn:population":0,
    "gn:timezone":"Africa/Malabo",
    "iso:country":"GQ",
    "wof:name":"Acombele",
    "wof:placetype":"locality"
},
  "geometry": {"coordinates":[10.52451,1.82461],"type":"Point"}
}