{
  "type": "Feature",
  "properties": {
    "gn:admin1_code":"00",
    "gn:asciiname":"Ncomo",
    "gn:country_code":"GQ",
    "gn:dem":446,
    "gn:feature_class":"P",
    "gn:feature_code":"PPL",
    "gn:name":"Ncomo",
    "gn:population":0,
    "gn:timezone":"Africa/Malabo",
    "iso:country":"GQ",
    "name:und_x_variant":[
        "Nkomo",
        "Ncomo"
    ],
    "wof:name":"Ncomo",
    "wof:placetype":"locality"
},
  "geometry": {"coordinates":[10.42245,1.86005],"type":"Point"}
}