{
  "type": "Feature",
  "properties": {
    "gn:admin1_code":"00",
    "gn:asciiname":"Mbam",
    "gn:country_code":"GQ",
    "gn:dem":635,
    "gn:feature_class":"P",
    "gn:feature_code":"PPL",
    "gn:name":"Mbam",
    "gn:population":0,
    "gn:timezone":"Africa/Malabo",
    "iso:country":"GQ",
    "wof:name":"Mbam",
    "wof:placetype":"locality"
},
  "geometry": {"coordinates":[11.32011,1.7111],"type":"Point"}
}