{
  "type": "Feature",
  "properties": {
    "gn:admin1_code":"00",
    "gn:asciiname":"Balombe",
    "gn:country_code":"GQ",
    "gn:dem":408,
    "gn:feature_class":"P",
    "gn:feature_code":"PPL",
    "gn:name":"Balombe",
    "gn:population":0,
    "gn:timezone":"Africa/Malabo",
    "iso:country":"GQ",
    "wof:name":"Balombe",
    "wof:placetype":"locality"
},
  "geometry": {"coordinates":[8.53333,3.43333],"type":"Point"}
}