{
  "type": "Feature",
  "properties": {
    "gn:admin1_code":"00",
    "gn:asciiname":"Mondoc",
    "gn:country_code":"GQ",
    "gn:dem":395,
    "gn:feature_class":"P",
    "gn:feature_code":"PPL",
    "gn:name":"Mondoc",
    "gn:population":0,
    "gn:timezone":"Africa/Malabo",
    "iso:country":"GQ",
    "wof:name":"Mondoc",
    "wof:placetype":"locality"
},
  "geometry": {"coordinates":[10.28065,1.77362],"type":"Point"}
}