{
  "type": "Feature",
  "properties": {
    "gn:admin1_code":"00",
    "gn:asciiname":"Nco",
    "gn:country_code":"GQ",
    "gn:dem":649,
    "gn:feature_class":"P",
    "gn:feature_code":"PPL",
    "gn:name":"Nco",
    "gn:population":0,
    "gn:timezone":"Africa/Malabo",
    "iso:country":"GQ",
    "wof:name":"Nco",
    "wof:placetype":"locality"
},
  "geometry": {"coordinates":[10.49598,1.70734],"type":"Point"}
}