{
  "type": "Feature",
  "properties": {
    "gn:admin1_code":"00",
    "gn:asciiname":"Bicaba",
    "gn:country_code":"GQ",
    "gn:dem":346,
    "gn:feature_class":"P",
    "gn:feature_code":"PPL",
    "gn:name":"Bicaba",
    "gn:population":0,
    "gn:timezone":"Africa/Malabo",
    "iso:country":"GQ",
    "name:und_x_variant":[
        "Bikaba",
        "Bicaba"
    ],
    "wof:name":"Bicaba",
    "wof:placetype":"locality"
},
  "geometry": {"coordinates":[10.26776,1.81117],"type":"Point"}
}