{
  "type": "Feature",
  "properties": {
    "gn:admin1_code":"00",
    "gn:asciiname":"Madyamebe",
    "gn:country_code":"GQ",
    "gn:dem":630,
    "gn:feature_class":"P",
    "gn:feature_code":"PPL",
    "gn:name":"Madyamebe",
    "gn:population":0,
    "gn:timezone":"Africa/Malabo",
    "iso:country":"GQ",
    "wof:name":"Madyamebe",
    "wof:placetype":"locality"
},
  "geometry": {"coordinates":[10.57535,1.23957],"type":"Point"}
}