{
  "type": "Feature",
  "properties": {
    "gn:admin1_code":"00",
    "gn:asciiname":"Micha",
    "gn:country_code":"GQ",
    "gn:dem":60,
    "gn:feature_class":"P",
    "gn:feature_code":"PPL",
    "gn:name":"Micha",
    "gn:population":0,
    "gn:timezone":"Africa/Malabo",
    "iso:country":"GQ",
    "name:und_x_variant":[
        "Michobo",
        "Micha"
    ],
    "wof:name":"Micha",
    "wof:placetype":"locality"
},
  "geometry": {"coordinates":[9.85866,1.20385],"type":"Point"}
}