{
  "type": "Feature",
  "properties": {
    "gn:admin1_code":"00",
    "gn:asciiname":"Ncomacac",
    "gn:country_code":"GQ",
    "gn:dem":52,
    "gn:feature_class":"P",
    "gn:feature_code":"PPL",
    "gn:name":"Ncomacac",
    "gn:population":0,
    "gn:timezone":"Africa/Malabo",
    "iso:country":"GQ",
    "wof:name":"Ncomacac",
    "wof:placetype":"locality"
},
  "geometry": {"coordinates":[9.88204,2.20293],"type":"Point"}
}