{
  "type": "Feature",
  "properties": {
    "gn:admin1_code":"00",
    "gn:asciiname":"Acoc",
    "gn:country_code":"GQ",
    "gn:dem":515,
    "gn:feature_class":"P",
    "gn:feature_code":"PPL",
    "gn:name":"Acoc",
    "gn:population":0,
    "gn:timezone":"Africa/Malabo",
    "iso:country":"GQ",
    "wof:name":"Acoc",
    "wof:placetype":"locality"
},
  "geometry": {"coordinates":[10.40143,2.07853],"type":"Point"}
}