{
  "type": "Feature",
  "properties": {
    "gn:admin1_code":"00",
    "gn:asciiname":"Acaasi",
    "gn:country_code":"GQ",
    "gn:dem":672,
    "gn:feature_class":"P",
    "gn:feature_code":"PPL",
    "gn:name":"Acaasi",
    "gn:population":0,
    "gn:timezone":"Africa/Malabo",
    "iso:country":"GQ",
    "wof:name":"Acaasi",
    "wof:placetype":"locality"
},
  "geometry": {"coordinates":[11.03119,1.32528],"type":"Point"}
}