{
  "type": "Feature",
  "properties": {
    "gn:admin1_code":"00",
    "gn:asciiname":"Bisobinam",
    "gn:country_code":"GQ",
    "gn:dem":35,
    "gn:feature_class":"P",
    "gn:feature_code":"PPL",
    "gn:name":"Bisobinam",
    "gn:population":0,
    "gn:timezone":"Africa/Malabo",
    "iso:country":"GQ",
    "wof:name":"Bisobinam",
    "wof:placetype":"locality"
},
  "geometry": {"coordinates":[9.40132,1.16596],"type":"Point"}
}