{
  "type": "Feature",
  "properties": {
    "gn:admin1_code":"00",
    "gn:asciiname":"Ayap",
    "gn:country_code":"GQ",
    "gn:dem":658,
    "gn:feature_class":"P",
    "gn:feature_code":"PPL",
    "gn:name":"Ayap",
    "gn:population":0,
    "gn:timezone":"Africa/Malabo",
    "iso:country":"GQ",
    "wof:name":"Ayap",
    "wof:placetype":"locality"
},
  "geometry": {"coordinates":[11.03949,1.68321],"type":"Point"}
}