{
  "type": "Feature",
  "properties": {
    "gn:admin1_code":"00",
    "gn:asciiname":"Buabe",
    "gn:country_code":"GQ",
    "gn:dem":40,
    "gn:feature_class":"P",
    "gn:feature_code":"PPL",
    "gn:name":"Buabe",
    "gn:population":0,
    "gn:timezone":"Africa/Malabo",
    "iso:country":"GQ",
    "wof:name":"Buabe",
    "wof:placetype":"locality"
},
  "geometry": {"coordinates":[9.78849,2.32599],"type":"Point"}
}