{
  "type": "Feature",
  "properties": {
    "gn:admin1_code":"00",
    "gn:asciiname":"Tegaete",
    "gn:country_code":"GQ",
    "gn:dem":456,
    "gn:feature_class":"P",
    "gn:feature_code":"PPL",
    "gn:name":"Tegaete",
    "gn:population":0,
    "gn:timezone":"Africa/Malabo",
    "iso:country":"GQ",
    "name:und_x_variant":[
        "Teguete",
        "Tegaete"
    ],
    "wof:name":"Tegaete",
    "wof:placetype":"locality"
},
  "geometry": {"coordinates":[10.28201,1.34109],"type":"Point"}
}