{
  "type": "Feature",
  "properties": {
    "gn:admin1_code":"00",
    "gn:asciiname":"Charman",
    "gn:country_code":"GQ",
    "gn:dem":511,
    "gn:feature_class":"P",
    "gn:feature_code":"PPL",
    "gn:name":"Charman",
    "gn:population":0,
    "gn:timezone":"Africa/Malabo",
    "iso:country":"GQ",
    "name:und_x_variant":[
        "Nchaman",
        "Charman"
    ],
    "wof:name":"Charman",
    "wof:placetype":"locality"
},
  "geometry": {"coordinates":[10.6949,2.09215],"type":"Point"}
}