{
  "type": "Feature",
  "properties": {
    "gn:admin1_code":"00",
    "gn:asciiname":"Mongoy",
    "gn:country_code":"GQ",
    "gn:dem":32,
    "gn:feature_class":"P",
    "gn:feature_code":"PPL",
    "gn:name":"Mongoy",
    "gn:population":0,
    "gn:timezone":"Africa/Malabo",
    "iso:country":"GQ",
    "name:und_x_variant":[
        "Mangoy",
        "Mongoy"
    ],
    "wof:name":"Mongoy",
    "wof:placetype":"locality"
},
  "geometry": {"coordinates":[9.61626,1.41099],"type":"Point"}
}