{
  "type": "Feature",
  "properties": {
    "gn:admin1_code":"00",
    "gn:asciiname":"Efulan",
    "gn:country_code":"GQ",
    "gn:dem":665,
    "gn:feature_class":"P",
    "gn:feature_code":"PPL",
    "gn:name":"Efulan",
    "gn:population":0,
    "gn:timezone":"Africa/Malabo",
    "iso:country":"GQ",
    "wof:name":"Efulan",
    "wof:placetype":"locality"
},
  "geometry": {"coordinates":[10.72475,1.34572],"type":"Point"}
}