{
  "type": "Feature",
  "properties": {
    "gn:admin1_code":"00",
    "gn:asciiname":"Mbominang",
    "gn:country_code":"GQ",
    "gn:dem":454,
    "gn:feature_class":"P",
    "gn:feature_code":"PPL",
    "gn:name":"Mbominang",
    "gn:population":0,
    "gn:timezone":"Africa/Malabo",
    "iso:country":"GQ",
    "wof:name":"Mbominang",
    "wof:placetype":"locality"
},
  "geometry": {"coordinates":[10.73214,1.94277],"type":"Point"}
}