{
  "type": "Feature",
  "properties": {
    "gn:admin1_code":"00",
    "gn:asciiname":"Elon",
    "gn:country_code":"GQ",
    "gn:dem":638,
    "gn:feature_class":"P",
    "gn:feature_code":"PPL",
    "gn:name":"Elon",
    "gn:population":0,
    "gn:timezone":"Africa/Malabo",
    "iso:country":"GQ",
    "name:ceb_x_preferred":[
        "Elon"
    ],
    "name:deu_x_preferred":[
        "Elon"
    ],
    "name:fra_x_preferred":[
        "Elon"
    ],
    "name:ita_x_preferred":[
        "Elon"
    ],
    "name:pol_x_preferred":[
        "Elon"
    ],
    "name:por_x_preferred":[
        "Elom"
    ],
    "name:rus_x_preferred":[
        "\u042d\u043b\u043e\u043d"
    ],
    "name:swe_x_preferred":[
        "Elon"
    ],
    "wof:name":"Elon",
    "wof:placetype":"locality"
},
  "geometry": {"coordinates":[11.29922,1.64671],"type":"Point"}
}