{
  "type": "Feature",
  "properties": {
    "gn:admin1_code":"00",
    "gn:asciiname":"Elon",
    "gn:country_code":"GQ",
    "gn:dem":638,
    "gn:feature_class":"P",
    "gn:feature_code":"PPL",
    "gn:name":"Elon",
    "gn:population":0,
    "gn:timezone":"Africa/Malabo",
    "iso:country":"GQ",
    "wof:name":"Elon",
    "wof:placetype":"locality"
},
  "geometry": {"coordinates":[11.29922,1.64671],"type":"Point"}
}