{
  "type": "Feature",
  "properties": {
    "gn:admin1_code":"00",
    "gn:asciiname":"Mbeayop",
    "gn:country_code":"GQ",
    "gn:dem":642,
    "gn:feature_class":"P",
    "gn:feature_code":"PPL",
    "gn:name":"Mbeayop",
    "gn:population":0,
    "gn:timezone":"Africa/Malabo",
    "iso:country":"GQ",
    "name:und_x_variant":[
        "Mbayop",
        "Mbeayop"
    ],
    "wof:name":"Mbeayop",
    "wof:placetype":"locality"
},
  "geometry": {"coordinates":[11.33805,1.6565],"type":"Point"}
}