{
  "type": "Feature",
  "properties": {
    "gn:admin1_code":"00",
    "gn:asciiname":"Adyamibang",
    "gn:country_code":"GQ",
    "gn:dem":650,
    "gn:feature_class":"P",
    "gn:feature_code":"PPL",
    "gn:name":"Adyamibang",
    "gn:population":0,
    "gn:timezone":"Africa/Malabo",
    "iso:country":"GQ",
    "wof:name":"Adyamibang",
    "wof:placetype":"locality"
},
  "geometry": {"coordinates":[10.51358,1.26135],"type":"Point"}
}