{
  "type": "Feature",
  "properties": {
    "gn:admin1_code":"00",
    "gn:asciiname":"Ebain",
    "gn:country_code":"GQ",
    "gn:dem":357,
    "gn:feature_class":"P",
    "gn:feature_code":"PPL",
    "gn:name":"Ebai\u00f1",
    "gn:population":0,
    "gn:timezone":"Africa/Malabo",
    "iso:country":"GQ",
    "wof:name":"Ebain",
    "wof:placetype":"locality"
},
  "geometry": {"coordinates":[10.20131,1.85227],"type":"Point"}
}