{
  "type": "Feature",
  "properties": {
    "gn:admin1_code":"00",
    "gn:asciiname":"Bison",
    "gn:country_code":"GQ",
    "gn:dem":614,
    "gn:feature_class":"P",
    "gn:feature_code":"PPL",
    "gn:name":"Bison",
    "gn:population":0,
    "gn:timezone":"Africa/Malabo",
    "iso:country":"GQ",
    "wof:name":"Bison",
    "wof:placetype":"locality"
},
  "geometry": {"coordinates":[11.29195,2.03081],"type":"Point"}
}