{
  "type": "Feature",
  "properties": {
    "gn:admin1_code":"00",
    "gn:asciiname":"Somo",
    "gn:country_code":"GQ",
    "gn:dem":591,
    "gn:feature_class":"P",
    "gn:feature_code":"PPL",
    "gn:name":"Somo",
    "gn:population":0,
    "gn:timezone":"Africa/Malabo",
    "iso:country":"GQ",
    "name:ceb_x_preferred":[
        "Somo"
    ],
    "name:fra_x_preferred":[
        "Somo"
    ],
    "name:ita_x_preferred":[
        "Somo"
    ],
    "name:nld_x_preferred":[
        "Somo"
    ],
    "name:spa_x_preferred":[
        "Somo"
    ],
    "name:swe_x_preferred":[
        "Somo"
    ],
    "wof:name":"Somo",
    "wof:placetype":"locality"
},
  "geometry": {"coordinates":[11.19452,2.18227],"type":"Point"}
}