{
  "type": "Feature",
  "properties": {
    "gn:admin1_code":"00",
    "gn:asciiname":"Bisong",
    "gn:country_code":"GQ",
    "gn:dem":476,
    "gn:feature_class":"P",
    "gn:feature_code":"PPL",
    "gn:name":"Bisong",
    "gn:population":0,
    "gn:timezone":"Africa/Malabo",
    "iso:country":"GQ",
    "wof:name":"Bisong",
    "wof:placetype":"locality"
},
  "geometry": {"coordinates":[10.31436,1.37209],"type":"Point"}
}