{
  "type": "Feature",
  "properties": {
    "gn:admin1_code":"00",
    "gn:asciiname":"Sua",
    "gn:country_code":"GQ",
    "gn:dem":533,
    "gn:feature_class":"P",
    "gn:feature_code":"PPL",
    "gn:name":"S\u00faa",
    "gn:population":0,
    "gn:timezone":"Africa/Malabo",
    "iso:country":"GQ",
    "wof:name":"Sua",
    "wof:placetype":"locality"
},
  "geometry": {"coordinates":[11.07246,0.99353],"type":"Point"}
}