{
  "type": "Feature",
  "properties": {
    "gn:admin1_code":"00",
    "gn:asciiname":"Anguma",
    "gn:country_code":"GQ",
    "gn:dem":107,
    "gn:feature_class":"P",
    "gn:feature_code":"PPL",
    "gn:name":"Anguma",
    "gn:population":0,
    "gn:timezone":"Africa/Malabo",
    "iso:country":"GQ",
    "name:und_x_variant":[
        "Angume",
        "Anguma"
    ],
    "wof:name":"Anguma",
    "wof:placetype":"locality"
},
  "geometry": {"coordinates":[10.10342,0.98394],"type":"Point"}
}