{
  "type": "Feature",
  "properties": {
    "gn:admin1_code":"00",
    "gn:asciiname":"Yiba",
    "gn:country_code":"GQ",
    "gn:dem":9,
    "gn:feature_class":"P",
    "gn:feature_code":"PPL",
    "gn:name":"Yiba",
    "gn:population":0,
    "gn:timezone":"Africa/Malabo",
    "iso:country":"GQ",
    "wof:name":"Yiba",
    "wof:placetype":"locality"
},
  "geometry": {"coordinates":[9.80431,1.88625],"type":"Point"}
}