{
  "type": "Feature",
  "properties": {
    "gn:admin1_code":"00",
    "gn:asciiname":"Michoo",
    "gn:country_code":"GQ",
    "gn:dem":656,
    "gn:feature_class":"P",
    "gn:feature_code":"PPL",
    "gn:name":"Michoo",
    "gn:population":0,
    "gn:timezone":"Africa/Malabo",
    "iso:country":"GQ",
    "wof:name":"Michoo",
    "wof:placetype":"locality"
},
  "geometry": {"coordinates":[10.48346,1.62287],"type":"Point"}
}