{
  "type": "Feature",
  "properties": {
    "gn:admin1_code":"00",
    "gn:asciiname":"Etong",
    "gn:country_code":"GQ",
    "gn:dem":468,
    "gn:feature_class":"P",
    "gn:feature_code":"PPL",
    "gn:name":"Etong",
    "gn:population":0,
    "gn:timezone":"Africa/Malabo",
    "iso:country":"GQ",
    "name:und_x_variant":[
        "Etom",
        "Etong"
    ],
    "wof:name":"Etong",
    "wof:placetype":"locality"
},
  "geometry": {"coordinates":[10.64558,1.82473],"type":"Point"}
}