{
  "type": "Feature",
  "properties": {
    "gn:admin1_code":"00",
    "gn:asciiname":"Ayene",
    "gn:country_code":"GQ",
    "gn:dem":617,
    "gn:feature_class":"P",
    "gn:feature_code":"PPL",
    "gn:name":"Ayene",
    "gn:population":0,
    "gn:timezone":"Africa/Malabo",
    "iso:country":"GQ",
    "name:cat_x_preferred":[
        "Ayene"
    ],
    "name:ceb_x_preferred":[
        "Ayene"
    ],
    "name:ita_x_preferred":[
        "Ayene"
    ],
    "name:pol_x_preferred":[
        "Ayene"
    ],
    "name:spa_x_preferred":[
        "Ayene"
    ],
    "name:swe_x_preferred":[
        "Ayene"
    ],
    "name:tur_x_preferred":[
        "Ayene"
    ],
    "wof:name":"Ayene",
    "wof:placetype":"locality"
},
  "geometry": {"coordinates":[10.30008,1.69728],"type":"Point"}
}