{
  "type": "Feature",
  "properties": {
    "gn:admin1_code":"00",
    "gn:asciiname":"Ecobenam",
    "gn:country_code":"GQ",
    "gn:dem":14,
    "gn:feature_class":"P",
    "gn:feature_code":"PPL",
    "gn:name":"Ecobenam",
    "gn:population":0,
    "gn:timezone":"Africa/Malabo",
    "iso:country":"GQ",
    "wof:name":"Ecobenam",
    "wof:placetype":"locality"
},
  "geometry": {"coordinates":[9.79045,1.859],"type":"Point"}
}