{
  "type": "Feature",
  "properties": {
    "gn:admin1_code":"00",
    "gn:asciiname":"Bidoma",
    "gn:country_code":"GQ",
    "gn:dem":49,
    "gn:feature_class":"P",
    "gn:feature_code":"PPL",
    "gn:name":"Bidoma",
    "gn:population":0,
    "gn:timezone":"Africa/Malabo",
    "iso:country":"GQ",
    "wof:name":"Bidoma",
    "wof:placetype":"locality"
},
  "geometry": {"coordinates":[9.82878,1.68312],"type":"Point"}
}