{
  "type": "Feature",
  "properties": {
    "gn:admin1_code":"00",
    "gn:asciiname":"Afaansoc",
    "gn:country_code":"GQ",
    "gn:dem":602,
    "gn:feature_class":"P",
    "gn:feature_code":"PPL",
    "gn:name":"Afaansoc",
    "gn:population":0,
    "gn:timezone":"Africa/Malabo",
    "iso:country":"GQ",
    "name:und_x_variant":[
        "Afa\u2019ansok",
        "Afaansoc"
    ],
    "wof:name":"Afaansoc",
    "wof:placetype":"locality"
},
  "geometry": {"coordinates":[10.77724,1.74442],"type":"Point"}
}