{
  "type": "Feature",
  "properties": {
    "gn:admin1_code":"00",
    "gn:asciiname":"Bimbon",
    "gn:country_code":"GQ",
    "gn:dem":148,
    "gn:feature_class":"P",
    "gn:feature_code":"PPL",
    "gn:name":"Bimbon",
    "gn:population":0,
    "gn:timezone":"Africa/Malabo",
    "iso:country":"GQ",
    "wof:name":"Bimbon",
    "wof:placetype":"locality"
},
  "geometry": {"coordinates":[9.924,1.84572],"type":"Point"}
}