{
  "type": "Feature",
  "properties": {
    "gn:admin1_code":"00",
    "gn:asciiname":"Bineng",
    "gn:country_code":"GQ",
    "gn:dem":47,
    "gn:feature_class":"P",
    "gn:feature_code":"PPL",
    "gn:name":"Bi\u00f1eng",
    "gn:population":0,
    "gn:timezone":"Africa/Malabo",
    "iso:country":"GQ",
    "wof:name":"Bineng",
    "wof:placetype":"locality"
},
  "geometry": {"coordinates":[9.86014,2.00592],"type":"Point"}
}