{
  "type": "Feature",
  "properties": {
    "gn:admin1_code":"00",
    "gn:asciiname":"Avelengong",
    "gn:country_code":"GQ",
    "gn:dem":499,
    "gn:feature_class":"P",
    "gn:feature_code":"PPL",
    "gn:name":"Avelengong",
    "gn:population":0,
    "gn:timezone":"Africa/Malabo",
    "iso:country":"GQ",
    "wof:name":"Avelengong",
    "wof:placetype":"locality"
},
  "geometry": {"coordinates":[10.02376,1.41016],"type":"Point"}
}