{
  "type": "Feature",
  "properties": {
    "gn:admin1_code":"00",
    "gn:asciiname":"Binguenguen",
    "gn:country_code":"GQ",
    "gn:dem":267,
    "gn:feature_class":"P",
    "gn:feature_code":"PPL",
    "gn:name":"Binguenguen",
    "gn:population":0,
    "gn:timezone":"Africa/Malabo",
    "iso:country":"GQ",
    "wof:name":"Binguenguen",
    "wof:placetype":"locality"
},
  "geometry": {"coordinates":[10.0755,1.70928],"type":"Point"}
}