{
  "type": "Feature",
  "properties": {
    "gn:admin1_code":"00",
    "gn:asciiname":"Andum",
    "gn:country_code":"GQ",
    "gn:dem":61,
    "gn:feature_class":"P",
    "gn:feature_code":"PPL",
    "gn:name":"Andum",
    "gn:population":0,
    "gn:timezone":"Africa/Malabo",
    "iso:country":"GQ",
    "wof:name":"Andum",
    "wof:placetype":"locality"
},
  "geometry": {"coordinates":[9.87859,1.9207],"type":"Point"}
}