{
  "type": "Feature",
  "properties": {
    "gn:admin1_code":"00",
    "gn:asciiname":"Nduma",
    "gn:country_code":"GQ",
    "gn:dem":479,
    "gn:feature_class":"P",
    "gn:feature_code":"PPL",
    "gn:name":"Nduma",
    "gn:population":0,
    "gn:timezone":"Africa/Malabo",
    "iso:country":"GQ",
    "wof:name":"Nduma",
    "wof:placetype":"locality"
},
  "geometry": {"coordinates":[10.56186,1.77059],"type":"Point"}
}