{
  "type": "Feature",
  "properties": {
    "gn:admin1_code":"00",
    "gn:asciiname":"Maule de Gaesa",
    "gn:country_code":"GQ",
    "gn:dem":351,
    "gn:feature_class":"P",
    "gn:feature_code":"PPL",
    "gn:name":"Maule de Gaesa",
    "gn:population":0,
    "gn:timezone":"Africa/Malabo",
    "iso:country":"GQ",
    "wof:name":"Maule de Gaesa",
    "wof:placetype":"locality"
},
  "geometry": {"coordinates":[8.71771,3.41559],"type":"Point"}
}