{
  "type": "Feature",
  "properties": {
    "gn:admin1_code":"00",
    "gn:asciiname":"Masoc",
    "gn:country_code":"GQ",
    "gn:dem":674,
    "gn:feature_class":"P",
    "gn:feature_code":"PPL",
    "gn:name":"Masoc",
    "gn:population":0,
    "gn:timezone":"Africa/Malabo",
    "iso:country":"GQ",
    "name:und_x_variant":[
        "Mosok",
        "Masoc"
    ],
    "wof:name":"Masoc",
    "wof:placetype":"locality"
},
  "geometry": {"coordinates":[10.84462,1.64952],"type":"Point"}
}