{
  "type": "Feature",
  "properties": {
    "gn:admin1_code":"00",
    "gn:asciiname":"Mfene",
    "gn:country_code":"GQ",
    "gn:dem":626,
    "gn:feature_class":"P",
    "gn:feature_code":"PPL",
    "gn:name":"Mfene",
    "gn:population":0,
    "gn:timezone":"Africa/Malabo",
    "iso:country":"GQ",
    "name:und_x_variant":[
        "Nfe\u00f1",
        "Mfene"
    ],
    "wof:name":"Mfene",
    "wof:placetype":"locality"
},
  "geometry": {"coordinates":[11.05368,1.87654],"type":"Point"}
}