{
  "type": "Feature",
  "properties": {
    "gn:admin1_code":"00",
    "gn:asciiname":"Anisoc",
    "gn:country_code":"GQ",
    "gn:dem":249,
    "gn:feature_class":"P",
    "gn:feature_code":"PPL",
    "gn:name":"A\u00f1isoc",
    "gn:population":0,
    "gn:timezone":"Africa/Malabo",
    "iso:country":"GQ",
    "wof:name":"Anisoc",
    "wof:placetype":"locality"
},
  "geometry": {"coordinates":[10.08559,1.72755],"type":"Point"}
}