{
  "type": "Feature",
  "properties": {
    "gn:admin1_code":"00",
    "gn:asciiname":"Asobla",
    "gn:country_code":"GQ",
    "gn:dem":21,
    "gn:feature_class":"P",
    "gn:feature_code":"PPL",
    "gn:name":"Asobla",
    "gn:population":0,
    "gn:timezone":"Africa/Malabo",
    "iso:country":"GQ",
    "wof:name":"Asobla",
    "wof:placetype":"locality"
},
  "geometry": {"coordinates":[9.96613,0.96568],"type":"Point"}
}