{
  "type": "Feature",
  "properties": {
    "gn:admin1_code":"00",
    "gn:asciiname":"Mayom",
    "gn:country_code":"GQ",
    "gn:dem":666,
    "gn:feature_class":"P",
    "gn:feature_code":"PPL",
    "gn:name":"Mayom",
    "gn:population":0,
    "gn:timezone":"Africa/Malabo",
    "iso:country":"GQ",
    "wof:name":"Mayom",
    "wof:placetype":"locality"
},
  "geometry": {"coordinates":[11.26631,1.25651],"type":"Point"}
}