{
  "type": "Feature",
  "properties": {
    "gn:admin1_code":"00",
    "gn:asciiname":"Abang",
    "gn:country_code":"GQ",
    "gn:dem":662,
    "gn:feature_class":"P",
    "gn:feature_code":"PPL",
    "gn:name":"Abang",
    "gn:population":0,
    "gn:timezone":"Africa/Malabo",
    "iso:country":"GQ",
    "wof:name":"Abang",
    "wof:placetype":"locality"
},
  "geometry": {"coordinates":[10.84347,1.63671],"type":"Point"}
}