{
  "type": "Feature",
  "properties": {
    "gn:admin1_code":"00",
    "gn:asciiname":"Mitombo",
    "gn:country_code":"GQ",
    "gn:dem":11,
    "gn:feature_class":"P",
    "gn:feature_code":"PPL",
    "gn:name":"Mitombo",
    "gn:population":0,
    "gn:timezone":"Africa/Malabo",
    "iso:country":"GQ",
    "wof:name":"Mitombo",
    "wof:placetype":"locality"
},
  "geometry": {"coordinates":[9.77654,1.10963],"type":"Point"}
}