{
  "type": "Feature",
  "properties": {
    "gn:admin1_code":"00",
    "gn:asciiname":"Bisobinam",
    "gn:country_code":"GQ",
    "gn:dem":461,
    "gn:feature_class":"P",
    "gn:feature_code":"PPL",
    "gn:name":"Bisobinam",
    "gn:population":0,
    "gn:timezone":"Africa/Malabo",
    "iso:country":"GQ",
    "wof:name":"Bisobinam",
    "wof:placetype":"locality"
},
  "geometry": {"coordinates":[10.67741,1.89876],"type":"Point"}
}