{
  "type": "Feature",
  "properties": {
    "gn:admin1_code":"00",
    "gn:asciiname":"Bao Basuala",
    "gn:country_code":"GQ",
    "gn:dem":301,
    "gn:feature_class":"P",
    "gn:feature_code":"PPL",
    "gn:name":"Ba\u00f3 Basuala",
    "gn:population":0,
    "gn:timezone":"Africa/Malabo",
    "iso:country":"GQ",
    "name:und_x_variant":[
        "Baho Basuala",
        "Ba\u00f3 Basuala"
    ],
    "wof:name":"Bao Basuala",
    "wof:placetype":"locality"
},
  "geometry": {"coordinates":[8.90685,3.63293],"type":"Point"}
}