{
  "type": "Feature",
  "properties": {
    "gn:admin1_code":"00",
    "gn:asciiname":"Alen",
    "gn:country_code":"GQ",
    "gn:dem":583,
    "gn:feature_class":"P",
    "gn:feature_code":"PPL",
    "gn:name":"Alen",
    "gn:population":0,
    "gn:timezone":"Africa/Malabo",
    "iso:country":"GQ",
    "name:ceb_x_preferred":[
        "Alen"
    ],
    "name:deu_x_preferred":[
        "Alen"
    ],
    "name:eus_x_preferred":[
        "Alen"
    ],
    "name:nld_x_preferred":[
        "Alen"
    ],
    "wof:name":"Alen",
    "wof:placetype":"locality"
},
  "geometry": {"coordinates":[11.3207,1.96459],"type":"Point"}
}