{
  "type": "Feature",
  "properties": {
    "gn:admin1_code":"00",
    "gn:asciiname":"Ndyengayong",
    "gn:cc2":"GQ",
    "gn:country_code":"GQ",
    "gn:dem":48,
    "gn:feature_class":"P",
    "gn:feature_code":"PPL",
    "gn:name":"Ndyengayong",
    "gn:population":0,
    "gn:timezone":"Africa/Malabo",
    "iso:country":"GQ",
    "name:und_x_variant":[
        "Nvengayong",
        "Ndyengayong"
    ],
    "wof:name":"Ndyengayong",
    "wof:placetype":"locality"
},
  "geometry": {"coordinates":[9.73333,1.68333],"type":"Point"}
}