{
  "type": "Feature",
  "properties": {
    "gn:admin1_code":"00",
    "gn:asciiname":"Mfulayong",
    "gn:country_code":"GQ",
    "gn:dem":483,
    "gn:feature_class":"P",
    "gn:feature_code":"PPL",
    "gn:name":"Mfulayong",
    "gn:population":0,
    "gn:timezone":"Africa/Malabo",
    "iso:country":"GQ",
    "name:und_x_variant":[
        "Nfulayong",
        "Mfulayong"
    ],
    "wof:name":"Mfulayong",
    "wof:placetype":"locality"
},
  "geometry": {"coordinates":[10.60386,1.97337],"type":"Point"}
}