{
  "type": "Feature",
  "properties": {
    "gn:admin1_code":"00",
    "gn:asciiname":"Nsangnam",
    "gn:country_code":"GQ",
    "gn:dem":594,
    "gn:feature_class":"P",
    "gn:feature_code":"PPL",
    "gn:name":"Nsangnam",
    "gn:population":0,
    "gn:timezone":"Africa/Malabo",
    "iso:country":"GQ",
    "wof:name":"Nsangnam",
    "wof:placetype":"locality"
},
  "geometry": {"coordinates":[10.40572,1.10722],"type":"Point"}
}