{
  "type": "Feature",
  "properties": {
    "gn:admin1_code":"00",
    "gn:asciiname":"Bicugo",
    "gn:country_code":"GQ",
    "gn:dem":476,
    "gn:feature_class":"P",
    "gn:feature_code":"PPL",
    "gn:name":"Bicugo",
    "gn:population":0,
    "gn:timezone":"Africa/Malabo",
    "iso:country":"GQ",
    "name:und_x_variant":[
        "Bikugo",
        "Bicugo"
    ],
    "wof:name":"Bicugo",
    "wof:placetype":"locality"
},
  "geometry": {"coordinates":[10.82869,1.85476],"type":"Point"}
}