{
  "type": "Feature",
  "properties": {
    "gn:admin1_code":"00",
    "gn:asciiname":"Evinayong",
    "gn:country_code":"GQ",
    "gn:dem":532,
    "gn:feature_class":"P",
    "gn:feature_code":"PPL",
    "gn:name":"Evinayong",
    "gn:population":0,
    "gn:timezone":"Africa/Malabo",
    "iso:country":"GQ",
    "name:cat_x_preferred":[
        "Evinayong"
    ],
    "name:ceb_x_preferred":[
        "Evinayong"
    ],
    "name:eus_x_preferred":[
        "Evinayong"
    ],
    "name:fas_x_preferred":[
        "\u0627\u0648\u06cc\u0646\u0627\u06cc\u0648\u0646\u06af"
    ],
    "name:fin_x_preferred":[
        "Evinayong"
    ],
    "name:fra_x_preferred":[
        "Evinayong"
    ],
    "name:frr_x_preferred":[
        "Evinayong"
    ],
    "name:heb_x_preferred":[
        "\u05d0\u05d5\u05d5\u05d9\u05e0\u05d9\u05d5\u05e0\u05d2"
    ],
    "name:hun_x_preferred":[
        "Evinayong"
    ],
    "name:ita_x_preferred":[
        "Evinayong"
    ],
    "name:jpn_x_preferred":[
        "\u30a8\u30f4\u30a3\u30ca\u30e8\u30f3\u30b0"
    ],
    "name:kor_x_preferred":[
        "\uc5d0\ube44\ub098\uc6a9"
    ],
    "name:lit_x_preferred":[
        "Evinajongas"
    ],
    "name:nld_x_preferred":[
        "Evinayong"
    ],
    "name:pol_x_preferred":[
        "Evinayong"
    ],
    "name:por_x_preferred":[
        "Evinayong"
    ],
    "name:ron_x_preferred":[
        "Evinayong"
    ],
    "name:rus_x_preferred":[
        "\u042d\u0432\u0438\u043d\u0430\u0439\u043e\u043d\u0433"
    ],
    "name:spa_x_preferred":[
        "Evinayong"
    ],
    "name:swe_x_preferred":[
        "Evinayong"
    ],
    "name:tur_x_preferred":[
        "Evinayong"
    ],
    "name:ukr_x_preferred":[
        "\u0415\u0432\u0456\u043d\u0430\u0439\u043e\u043d\u0491"
    ],
    "name:zho_x_preferred":[
        "\u57c3\u7dad\u7d0d\u6c38"
    ],
    "wof:name":"Evinayong",
    "wof:placetype":"locality"
},
  "geometry": {"coordinates":[10.2755,1.09407],"type":"Point"}
}