{
  "type": "Feature",
  "properties": {
    "gn:admin1_code":"00",
    "gn:asciiname":"Amvonga",
    "gn:country_code":"GQ",
    "gn:dem":665,
    "gn:feature_class":"P",
    "gn:feature_code":"PPL",
    "gn:name":"Amvonga",
    "gn:population":0,
    "gn:timezone":"Africa/Malabo",
    "iso:country":"GQ",
    "name:und_x_variant":[
        "Anvonga",
        "Amvonga"
    ],
    "wof:name":"Amvonga",
    "wof:placetype":"locality"
},
  "geometry": {"coordinates":[10.57745,1.31898],"type":"Point"}
}