{
  "type": "Feature",
  "properties": {
    "gn:admin1_code":"00",
    "gn:asciiname":"Niasam",
    "gn:country_code":"GQ",
    "gn:dem":45,
    "gn:feature_class":"P",
    "gn:feature_code":"PPL",
    "gn:name":"Niasam",
    "gn:population":0,
    "gn:timezone":"Africa/Malabo",
    "iso:country":"GQ",
    "wof:name":"Niasam",
    "wof:placetype":"locality"
},
  "geometry": {"coordinates":[9.83396,2.02226],"type":"Point"}
}