{
  "type": "Feature",
  "properties": {
    "gn:admin1_code":"00",
    "gn:asciiname":"Ntobo",
    "gn:country_code":"GQ",
    "gn:dem":17,
    "gn:feature_class":"P",
    "gn:feature_code":"PPL",
    "gn:name":"Ntobo",
    "gn:population":0,
    "gn:timezone":"Africa/Malabo",
    "iso:country":"GQ",
    "wof:name":"Ntobo",
    "wof:placetype":"locality"
},
  "geometry": {"coordinates":[9.77502,1.80268],"type":"Point"}
}