{
  "type": "Feature",
  "properties": {
    "gn:admin1_code":"00",
    "gn:asciiname":"Minlom",
    "gn:country_code":"GQ",
    "gn:dem":556,
    "gn:feature_class":"P",
    "gn:feature_code":"PPL",
    "gn:name":"Minlom",
    "gn:population":0,
    "gn:timezone":"Africa/Malabo",
    "iso:country":"GQ",
    "wof:name":"Minlom",
    "wof:placetype":"locality"
},
  "geometry": {"coordinates":[10.24194,1.11469],"type":"Point"}
}