{
  "type": "Feature",
  "properties": {
    "gn:admin1_code":"00",
    "gn:asciiname":"Endenden",
    "gn:country_code":"GQ",
    "gn:dem":381,
    "gn:feature_class":"P",
    "gn:feature_code":"PPL",
    "gn:name":"Endenden",
    "gn:population":0,
    "gn:timezone":"Africa/Malabo",
    "iso:country":"GQ",
    "wof:name":"Endenden",
    "wof:placetype":"locality"
},
  "geometry": {"coordinates":[10.26875,1.96569],"type":"Point"}
}