{
  "type": "Feature",
  "properties": {
    "gn:admin1_code":"00",
    "gn:asciiname":"Adyabasi",
    "gn:country_code":"GQ",
    "gn:dem":661,
    "gn:feature_class":"P",
    "gn:feature_code":"PPL",
    "gn:name":"Adyabasi",
    "gn:population":0,
    "gn:timezone":"Africa/Malabo",
    "iso:country":"GQ",
    "wof:name":"Adyabasi",
    "wof:placetype":"locality"
},
  "geometry": {"coordinates":[10.47392,1.50578],"type":"Point"}
}