{
  "type": "Feature",
  "properties": {
    "gn:admin1_code":"00",
    "gn:asciiname":"Mbe",
    "gn:country_code":"GQ",
    "gn:dem":463,
    "gn:feature_class":"P",
    "gn:feature_code":"PPL",
    "gn:name":"Mbe",
    "gn:population":0,
    "gn:timezone":"Africa/Malabo",
    "iso:country":"GQ",
    "name:ceb_x_preferred":[
        "Mbe"
    ],
    "name:swe_x_preferred":[
        "Mbe"
    ],
    "name:und_x_variant":[
        "Mba",
        "Mbe"
    ],
    "wof:name":"Mbe",
    "wof:placetype":"locality"
},
  "geometry": {"coordinates":[10.42318,1.80641],"type":"Point"}
}