{
  "type": "Feature",
  "properties": {
    "gn:admin1_code":"00",
    "gn:asciiname":"Tepe",
    "gn:country_code":"GQ",
    "gn:dem":234,
    "gn:feature_class":"P",
    "gn:feature_code":"PPL",
    "gn:name":"Tep\u00e9",
    "gn:population":0,
    "gn:timezone":"Africa/Malabo",
    "iso:country":"GQ",
    "name:und_x_variant":[
        "Tope",
        "Tep\u00e9"
    ],
    "wof:name":"Tepe",
    "wof:placetype":"locality"
},
  "geometry": {"coordinates":[8.91633,3.68166],"type":"Point"}
}