{
  "type": "Feature",
  "properties": {
    "gn:admin1_code":"00",
    "gn:asciiname":"Ebansoc",
    "gn:country_code":"GQ",
    "gn:dem":385,
    "gn:feature_class":"P",
    "gn:feature_code":"PPL",
    "gn:name":"Ebansoc",
    "gn:population":0,
    "gn:timezone":"Africa/Malabo",
    "iso:country":"GQ",
    "name:und_x_variant":[
        "Ebansok",
        "Ebansoc"
    ],
    "wof:name":"Ebansoc",
    "wof:placetype":"locality"
},
  "geometry": {"coordinates":[10.25819,1.95076],"type":"Point"}
}