{
  "type": "Feature",
  "properties": {
    "gn:admin1_code":"00",
    "gn:asciiname":"Mbe",
    "gn:country_code":"GQ",
    "gn:dem":61,
    "gn:feature_class":"P",
    "gn:feature_code":"PPL",
    "gn:name":"Mbe",
    "gn:population":0,
    "gn:timezone":"Africa/Malabo",
    "iso:country":"GQ",
    "name:und_x_variant":[
        "Mbel",
        "Mbele",
        "Mbe"
    ],
    "wof:name":"Mbe",
    "wof:placetype":"locality"
},
  "geometry": {"coordinates":[9.83039,1.20835],"type":"Point"}
}