{
  "type": "Feature",
  "properties": {
    "gn:admin1_code":"00",
    "gn:asciiname":"Ncoanen",
    "gn:country_code":"GQ",
    "gn:dem":459,
    "gn:feature_class":"P",
    "gn:feature_code":"PPL",
    "gn:name":"Ncoanen",
    "gn:population":0,
    "gn:timezone":"Africa/Malabo",
    "iso:country":"GQ",
    "name:und_x_variant":[
        "Nko Anem-Manike",
        "Nko Anem-Manique",
        "Ncoanen"
    ],
    "wof:name":"Ncoanen",
    "wof:placetype":"locality"
},
  "geometry": {"coordinates":[10.58616,2.04807],"type":"Point"}
}