{
  "type": "Feature",
  "properties": {
    "gn:admin1_code":"00",
    "gn:asciiname":"Selies",
    "gn:country_code":"GQ",
    "gn:dem":30,
    "gn:feature_class":"P",
    "gn:feature_code":"PPL",
    "gn:name":"Selies",
    "gn:population":0,
    "gn:timezone":"Africa/Malabo",
    "iso:country":"GQ",
    "name:und_x_variant":[
        "Seleye",
        "Selies"
    ],
    "wof:name":"Selies",
    "wof:placetype":"locality"
},
  "geometry": {"coordinates":[9.83142,1.95838],"type":"Point"}
}