{
  "type": "Feature",
  "properties": {
    "gn:admin1_code":"00",
    "gn:asciiname":"Ntu",
    "gn:country_code":"GQ",
    "gn:dem":611,
    "gn:feature_class":"P",
    "gn:feature_code":"PPL",
    "gn:name":"Ntu",
    "gn:population":0,
    "gn:timezone":"Africa/Malabo",
    "iso:country":"GQ",
    "wof:name":"Ntu",
    "wof:placetype":"locality"
},
  "geometry": {"coordinates":[11.36986,1.87332],"type":"Point"}
}