{
  "type": "Feature",
  "properties": {
    "gn:admin1_code":"00",
    "gn:asciiname":"Abiara",
    "gn:country_code":"GQ",
    "gn:dem":686,
    "gn:feature_class":"P",
    "gn:feature_code":"PPL",
    "gn:name":"Abiara",
    "gn:population":0,
    "gn:timezone":"Africa/Malabo",
    "iso:country":"GQ",
    "wof:name":"Abiara",
    "wof:placetype":"locality"
},
  "geometry": {"coordinates":[10.99107,1.33537],"type":"Point"}
}