{
  "type": "Feature",
  "properties": {
    "gn:admin1_code":"00",
    "gn:asciiname":"Enuc",
    "gn:country_code":"GQ",
    "gn:dem":675,
    "gn:feature_class":"P",
    "gn:feature_code":"PPL",
    "gn:name":"Enuc",
    "gn:population":0,
    "gn:timezone":"Africa/Malabo",
    "iso:country":"GQ",
    "wof:name":"Enuc",
    "wof:placetype":"locality"
},
  "geometry": {"coordinates":[11.30356,1.53743],"type":"Point"}
}