{
  "type": "Feature",
  "properties": {
    "gn:admin1_code":"00",
    "gn:asciiname":"Efon",
    "gn:country_code":"GQ",
    "gn:dem":585,
    "gn:feature_class":"P",
    "gn:feature_code":"PPL",
    "gn:name":"Efon",
    "gn:population":0,
    "gn:timezone":"Africa/Malabo",
    "iso:country":"GQ",
    "name:und_x_variant":[
        "Efong",
        "Efon"
    ],
    "wof:name":"Efon",
    "wof:placetype":"locality"
},
  "geometry": {"coordinates":[10.26278,1.00172],"type":"Point"}
}