{
  "type": "Feature",
  "properties": {
    "gn:admin1_code":"00",
    "gn:asciiname":"Ayaaman",
    "gn:country_code":"GQ",
    "gn:dem":463,
    "gn:feature_class":"P",
    "gn:feature_code":"PPL",
    "gn:name":"Ayaaman",
    "gn:population":0,
    "gn:timezone":"Africa/Malabo",
    "iso:country":"GQ",
    "wof:name":"Ayaaman",
    "wof:placetype":"locality"
},
  "geometry": {"coordinates":[10.82498,1.93896],"type":"Point"}
}