{
  "type": "Feature",
  "properties": {
    "gn:admin1_code":"00",
    "gn:asciiname":"Madrid",
    "gn:country_code":"GQ",
    "gn:dem":7,
    "gn:feature_class":"P",
    "gn:feature_code":"PPL",
    "gn:name":"Madrid",
    "gn:population":0,
    "gn:timezone":"Africa/Malabo",
    "iso:country":"GQ",
    "wof:name":"Madrid",
    "wof:placetype":"locality"
},
  "geometry": {"coordinates":[9.6934,1.0879],"type":"Point"}
}