{
  "type": "Feature",
  "properties": {
    "gn:admin1_code":"00",
    "gn:asciiname":"Ruiche",
    "gn:country_code":"GQ",
    "gn:dem":829,
    "gn:feature_class":"P",
    "gn:feature_code":"PPL",
    "gn:name":"Ruich\u00e9",
    "gn:population":0,
    "gn:timezone":"Africa/Malabo",
    "iso:country":"GQ",
    "name:und_x_variant":[
        "Buchica",
        "Ruicha",
        "Ruich\u00e9"
    ],
    "wof:name":"Ruiche",
    "wof:placetype":"locality"
},
  "geometry": {"coordinates":[8.54986,3.41067],"type":"Point"}
}