{
  "type": "Feature",
  "properties": {
    "gn:country":"GQ",
    "gn:fcode":"PPL",
    "gn:pop":1464,
    "iso:country":"GQ",
    "name:cat_x_preferred":[
        "Bitika"
    ],
    "name:dut_x_preferred":[
        "Bitica"
    ],
    "name:eng_x_preferred":[
        "Bitica"
    ],
    "name:fre_x_preferred":[
        "Bitica"
    ],
    "name:ita_x_preferred":[
        "Bitica"
    ],
    "name:spa_x_preferred":[
        "Bitica"
    ],
    "name:swe_x_preferred":[
        "Bitica"
    ],
    "name:tur_x_preferred":[
        "Bitica"
    ],
    "name:unk_x_variant":[
        "Bitika"
    ],
    "qs:name":"Bitica",
    "qs:photos_9r":0,
    "qs:photos_sr":0,
    "qs:pop_sr":"3",
    "wd:wordcount":38,
    "wof:name":"Bitica",
    "wof:placetype":"locality",
    "wof:population":1464
},
  "geometry": {"coordinates":[9.62316,1.4261],"type":"Point"}
}