{
  "type": "Feature",
  "properties": {
    "gn:admin1_code":"00",
    "gn:asciiname":"Botenos",
    "gn:cc2":"GQ",
    "gn:country_code":"GQ",
    "gn:dem":105,
    "gn:feature_class":"P",
    "gn:feature_code":"PPL",
    "gn:name":"Boten\u00f3s",
    "gn:population":0,
    "gn:timezone":"Africa/Malabo",
    "iso:country":"GQ",
    "name:und_x_variant":[
        "Botonos",
        "Boten\u00f3s"
    ],
    "wof:name":"Botenos",
    "wof:placetype":"locality"
},
  "geometry": {"coordinates":[8.63333,3.66667],"type":"Point"}
}