{
  "type": "Feature",
  "properties": {
    "gn:admin1_code":"00",
    "gn:asciiname":"Macoga",
    "gn:country_code":"GQ",
    "gn:dem":612,
    "gn:feature_class":"P",
    "gn:feature_code":"PPL",
    "gn:name":"Macoga",
    "gn:population":0,
    "gn:timezone":"Africa/Malabo",
    "iso:country":"GQ",
    "name:und_x_variant":[
        "Makoga",
        "Macoga"
    ],
    "wof:name":"Macoga",
    "wof:placetype":"locality"
},
  "geometry": {"coordinates":[11.24882,1.80642],"type":"Point"}
}