{
  "type": "Feature",
  "properties": {
    "gn:admin1_code":"00",
    "gn:asciiname":"Bifet",
    "gn:country_code":"GQ",
    "gn:dem":603,
    "gn:feature_class":"P",
    "gn:feature_code":"PPL",
    "gn:name":"Bifet",
    "gn:population":0,
    "gn:timezone":"Africa/Malabo",
    "iso:country":"GQ",
    "name:und_x_variant":[
        "Bifee",
        "Bifet"
    ],
    "wof:name":"Bifet",
    "wof:placetype":"locality"
},
  "geometry": {"coordinates":[11.26849,2.06977],"type":"Point"}
}