{
  "type": "Feature",
  "properties": {
    "gn:admin1_code":"00",
    "gn:asciiname":"Andon",
    "gn:country_code":"GQ",
    "gn:dem":603,
    "gn:feature_class":"P",
    "gn:feature_code":"PPL",
    "gn:name":"Andon",
    "gn:population":0,
    "gn:timezone":"Africa/Malabo",
    "iso:country":"GQ",
    "name:deu_x_preferred":[
        "Andon"
    ],
    "name:fra_x_preferred":[
        "Andon"
    ],
    "name:rus_x_preferred":[
        "\u0410\u043d\u0434\u043e\u043d"
    ],
    "name:slk_x_preferred":[
        "Andon"
    ],
    "name:spa_x_preferred":[
        "Andon"
    ],
    "name:swe_x_preferred":[
        "Andon"
    ],
    "name:und_x_variant":[
        "Andom",
        "Andon"
    ],
    "wof:name":"Andon",
    "wof:placetype":"locality"
},
  "geometry": {"coordinates":[10.96811,2.02646],"type":"Point"}
}