{
  "type": "Feature",
  "properties": {
    "gn:admin1_code":"00",
    "gn:asciiname":"Nasanga",
    "gn:country_code":"GQ",
    "gn:dem":42,
    "gn:feature_class":"P",
    "gn:feature_code":"PPL",
    "gn:name":"\u00d1asanga",
    "gn:population":0,
    "gn:timezone":"Africa/Malabo",
    "iso:country":"GQ",
    "name:und_x_variant":[
        "\u00d1ansang",
        "\u00d1asanga"
    ],
    "wof:name":"Nasanga",
    "wof:placetype":"locality"
},
  "geometry": {"coordinates":[9.8537,1.98165],"type":"Point"}
}