{
  "type": "Feature",
  "properties": {
    "gn:admin1_code":"00",
    "gn:asciiname":"Obandoc",
    "gn:country_code":"GQ",
    "gn:dem":566,
    "gn:feature_class":"P",
    "gn:feature_code":"PPL",
    "gn:name":"Obandoc",
    "gn:population":0,
    "gn:timezone":"Africa/Malabo",
    "iso:country":"GQ",
    "name:und_x_variant":[
        "Ovandoc",
        "Obandoc"
    ],
    "wof:name":"Obandoc",
    "wof:placetype":"locality"
},
  "geometry": {"coordinates":[10.37672,1.1497],"type":"Point"}
}