{
  "type": "Feature",
  "properties": {
    "gn:admin1_code":"00",
    "gn:asciiname":"Utonde",
    "gn:country_code":"GQ",
    "gn:dem":7,
    "gn:feature_class":"P",
    "gn:feature_code":"PPL",
    "gn:name":"Utonde",
    "gn:population":0,
    "gn:timezone":"Africa/Malabo",
    "iso:country":"GQ",
    "name:und_x_variant":[
        "Utande",
        "Otondo",
        "Otonde",
        "Utonde"
    ],
    "wof:name":"Utonde",
    "wof:placetype":"locality"
},
  "geometry": {"coordinates":[9.81594,1.94002],"type":"Point"}
}