{
  "type": "Feature",
  "properties": {
    "gn:admin1_code":"00",
    "gn:asciiname":"Eburu",
    "gn:country_code":"GQ",
    "gn:dem":181,
    "gn:feature_class":"P",
    "gn:feature_code":"PPL",
    "gn:name":"Eburu",
    "gn:population":0,
    "gn:timezone":"Africa/Malabo",
    "iso:country":"GQ",
    "wof:name":"Eburu",
    "wof:placetype":"locality"
},
  "geometry": {"coordinates":[8.73849,3.30579],"type":"Point"}
}