{
  "type": "Feature",
  "properties": {
    "gn:admin1_code":"00",
    "gn:asciiname":"Asuiabe",
    "gn:country_code":"GQ",
    "gn:dem":66,
    "gn:feature_class":"P",
    "gn:feature_code":"PPL",
    "gn:name":"Asuiabe",
    "gn:population":0,
    "gn:timezone":"Africa/Malabo",
    "iso:country":"GQ",
    "wof:name":"Asuiabe",
    "wof:placetype":"locality"
},
  "geometry": {"coordinates":[9.62715,1.20324],"type":"Point"}
}