{
  "type": "Feature",
  "properties": {
    "gn:admin1_code":"00",
    "gn:asciiname":"Camferec",
    "gn:country_code":"GQ",
    "gn:dem":3,
    "gn:feature_class":"P",
    "gn:feature_code":"PPL",
    "gn:name":"Camferec",
    "gn:population":0,
    "gn:timezone":"Africa/Malabo",
    "iso:country":"GQ",
    "name:und_x_variant":[
        "Kamfere",
        "Kanfere",
        "Camferec"
    ],
    "wof:name":"Camferec",
    "wof:placetype":"locality"
},
  "geometry": {"coordinates":[9.43861,1.11535],"type":"Point"}
}