{
  "type": "Feature",
  "properties": {
    "gn:admin1_code":"00",
    "gn:asciiname":"Engong",
    "gn:country_code":"GQ",
    "gn:dem":513,
    "gn:feature_class":"P",
    "gn:feature_code":"PPL",
    "gn:name":"Engong",
    "gn:population":0,
    "gn:timezone":"Africa/Malabo",
    "iso:country":"GQ",
    "wof:name":"Engong",
    "wof:placetype":"locality"
},
  "geometry": {"coordinates":[10.01239,1.40729],"type":"Point"}
}