{
  "type": "Feature",
  "properties": {
    "gn:admin1_code":"00",
    "gn:asciiname":"Janye",
    "gn:country_code":"GQ",
    "gn:dem":38,
    "gn:feature_class":"P",
    "gn:feature_code":"PPL",
    "gn:name":"Janye",
    "gn:population":0,
    "gn:timezone":"Africa/Malabo",
    "iso:country":"GQ",
    "wof:name":"Janye",
    "wof:placetype":"locality"
},
  "geometry": {"coordinates":[9.53508,1.44392],"type":"Point"}
}