{
  "type": "Feature",
  "properties": {
    "gn:admin1_code":"00",
    "gn:asciiname":"Bidogo",
    "gn:country_code":"GQ",
    "gn:dem":408,
    "gn:feature_class":"P",
    "gn:feature_code":"PPL",
    "gn:name":"Bidogo",
    "gn:population":0,
    "gn:timezone":"Africa/Malabo",
    "iso:country":"GQ",
    "wof:name":"Bidogo",
    "wof:placetype":"locality"
},
  "geometry": {"coordinates":[10.13402,1.10183],"type":"Point"}
}