{
  "type": "Feature",
  "properties": {
    "gn:admin1_code":"00",
    "gn:asciiname":"Ecumeben",
    "gn:country_code":"GQ",
    "gn:dem":380,
    "gn:feature_class":"P",
    "gn:feature_code":"PPL",
    "gn:name":"Ecumebe\u00f1",
    "gn:population":0,
    "gn:timezone":"Africa/Malabo",
    "iso:country":"GQ",
    "name:und_x_variant":[
        "Ekumebain",
        "Ecumebe\u00f1"
    ],
    "wof:name":"Ecumeben",
    "wof:placetype":"locality"
},
  "geometry": {"coordinates":[10.27555,1.97376],"type":"Point"}
}