{
  "type": "Feature",
  "properties": {
    "gn:admin1_code":"00",
    "gn:asciiname":"Izaguirre",
    "gn:country_code":"GQ",
    "gn:dem":18,
    "gn:feature_class":"P",
    "gn:feature_code":"PPL",
    "gn:name":"Izaguirre",
    "gn:population":0,
    "gn:timezone":"Africa/Malabo",
    "iso:country":"GQ",
    "wof:name":"Izaguirre",
    "wof:placetype":"locality"
},
  "geometry": {"coordinates":[9.65,1.61667],"type":"Point"}
}