{
  "type": "Feature",
  "properties": {
    "gn:admin1_code":"00",
    "gn:asciiname":"Nnoayong",
    "gn:country_code":"GQ",
    "gn:dem":456,
    "gn:feature_class":"P",
    "gn:feature_code":"PPL",
    "gn:name":"Nnoayong",
    "gn:population":0,
    "gn:timezone":"Africa/Malabo",
    "iso:country":"GQ",
    "name:und_x_variant":[
        "Nloayong",
        "Nnoayong"
    ],
    "wof:name":"Nnoayong",
    "wof:placetype":"locality"
},
  "geometry": {"coordinates":[10.82017,1.89963],"type":"Point"}
}