{
  "type": "Feature",
  "properties": {
    "gn:admin1_code":"00",
    "gn:asciiname":"Asoc",
    "gn:country_code":"GQ",
    "gn:dem":504,
    "gn:feature_class":"P",
    "gn:feature_code":"PPL",
    "gn:name":"Asoc",
    "gn:population":0,
    "gn:timezone":"Africa/Malabo",
    "iso:country":"GQ",
    "name:und_x_variant":[
        "Asok",
        "Asoc"
    ],
    "wof:name":"Asoc",
    "wof:placetype":"locality"
},
  "geometry": {"coordinates":[10.61,1.75677],"type":"Point"}
}