{
  "type": "Feature",
  "properties": {
    "gn:admin1_code":"00",
    "gn:asciiname":"Obenelang",
    "gn:country_code":"GQ",
    "gn:dem":446,
    "gn:feature_class":"P",
    "gn:feature_code":"PPL",
    "gn:name":"Obenelang",
    "gn:population":0,
    "gn:timezone":"Africa/Malabo",
    "iso:country":"GQ",
    "wof:name":"Obenelang",
    "wof:placetype":"locality"
},
  "geometry": {"coordinates":[10.50393,1.86605],"type":"Point"}
}