{
  "type": "Feature",
  "properties": {
    "gn:admin1_code":"00",
    "gn:asciiname":"Ncum",
    "gn:country_code":"GQ",
    "gn:dem":635,
    "gn:feature_class":"P",
    "gn:feature_code":"PPL",
    "gn:name":"Ncum",
    "gn:population":0,
    "gn:timezone":"Africa/Malabo",
    "iso:country":"GQ",
    "name:und_x_variant":[
        "Nkum",
        "Ncum"
    ],
    "wof:name":"Ncum",
    "wof:placetype":"locality"
},
  "geometry": {"coordinates":[11.18772,1.8882],"type":"Point"}
}