{
  "type": "Feature",
  "properties": {
    "gn:admin1_code":"00",
    "gn:asciiname":"Abang",
    "gn:country_code":"GQ",
    "gn:dem":457,
    "gn:feature_class":"P",
    "gn:feature_code":"PPL",
    "gn:name":"Abang",
    "gn:population":0,
    "gn:timezone":"Africa/Malabo",
    "iso:country":"GQ",
    "name:ceb_x_preferred":[
        "Abang"
    ],
    "name:fra_x_preferred":[
        "Abang"
    ],
    "name:msa_x_preferred":[
        "Abang"
    ],
    "name:swe_x_preferred":[
        "Abang"
    ],
    "name:tgl_x_preferred":[
        "Abang"
    ],
    "name:tyv_x_preferred":[
        "\u0410\u0431\u0430\u043d\u0433"
    ],
    "wof:name":"Abang",
    "wof:placetype":"locality"
},
  "geometry": {"coordinates":[10.76619,1.92762],"type":"Point"}
}