{
  "type": "Feature",
  "properties": {
    "gn:admin1_code":"00",
    "gn:asciiname":"Elat",
    "gn:country_code":"GQ",
    "gn:dem":404,
    "gn:feature_class":"P",
    "gn:feature_code":"PPL",
    "gn:name":"Elat",
    "gn:population":0,
    "gn:timezone":"Africa/Malabo",
    "iso:country":"GQ",
    "wof:name":"Elat",
    "wof:placetype":"locality"
},
  "geometry": {"coordinates":[10.47775,2.05014],"type":"Point"}
}