{
  "type": "Feature",
  "properties": {
    "gn:admin1_code":"00",
    "gn:asciiname":"Deogracias",
    "gn:country_code":"GQ",
    "gn:dem":17,
    "gn:feature_class":"P",
    "gn:feature_code":"PPL",
    "gn:name":"Deogracias",
    "gn:population":0,
    "gn:timezone":"Africa/Malabo",
    "iso:country":"GQ",
    "wof:name":"Deogracias",
    "wof:placetype":"locality"
},
  "geometry": {"coordinates":[9.61461,1.57707],"type":"Point"}
}