{
  "type": "Feature",
  "properties": {
    "gn:admin1_code":"00",
    "gn:asciiname":"Andom",
    "gn:country_code":"GQ",
    "gn:dem":568,
    "gn:feature_class":"P",
    "gn:feature_code":"PPL",
    "gn:name":"Andom",
    "gn:population":0,
    "gn:timezone":"Africa/Malabo",
    "iso:country":"GQ",
    "wof:name":"Andom",
    "wof:placetype":"locality"
},
  "geometry": {"coordinates":[10.59869,1.76478],"type":"Point"}
}