{
  "type": "Feature",
  "properties": {
    "gn:admin1_code":"00",
    "gn:asciiname":"Ncumekie",
    "gn:country_code":"GQ",
    "gn:dem":35,
    "gn:feature_class":"P",
    "gn:feature_code":"PPL",
    "gn:name":"Ncumeki\u00e9",
    "gn:population":0,
    "gn:timezone":"Africa/Malabo",
    "iso:country":"GQ",
    "name:und_x_variant":[
        "Nkumekie",
        "Ncumeki\u00e9"
    ],
    "wof:name":"Ncumekie",
    "wof:placetype":"locality"
},
  "geometry": {"coordinates":[9.69231,1.51526],"type":"Point"}
}