{
  "type": "Feature",
  "properties": {
    "gn:admin1_code":"00",
    "gn:asciiname":"Nco",
    "gn:country_code":"GQ",
    "gn:dem":473,
    "gn:feature_class":"P",
    "gn:feature_code":"PPL",
    "gn:name":"Nco",
    "gn:population":0,
    "gn:timezone":"Africa/Malabo",
    "iso:country":"GQ",
    "name:und_x_variant":[
        "Nko",
        "Nco"
    ],
    "wof:name":"Nco",
    "wof:placetype":"locality"
},
  "geometry": {"coordinates":[10.57497,1.82885],"type":"Point"}
}