{
  "type": "Feature",
  "properties": {
    "gn:admin1_code":"00",
    "gn:asciiname":"Minsengminsoc",
    "gn:country_code":"GQ",
    "gn:dem":596,
    "gn:feature_class":"P",
    "gn:feature_code":"PPL",
    "gn:name":"Minsengminsoc",
    "gn:population":0,
    "gn:timezone":"Africa/Malabo",
    "iso:country":"GQ",
    "name:und_x_variant":[
        "Misemisok",
        "Minsengminsoc"
    ],
    "wof:name":"Minsengminsoc",
    "wof:placetype":"locality"
},
  "geometry": {"coordinates":[10.4637,1.13668],"type":"Point"}
}