{
  "type": "Feature",
  "properties": {
    "gn:admin1_code":"00",
    "gn:asciiname":"Mebaya",
    "gn:country_code":"GQ",
    "gn:dem":30,
    "gn:feature_class":"P",
    "gn:feature_code":"PPL",
    "gn:name":"Mebaya",
    "gn:population":0,
    "gn:timezone":"Africa/Malabo",
    "iso:country":"GQ",
    "name:und_x_variant":[
        "Mibaia",
        "Mebaya"
    ],
    "wof:name":"Mebaya",
    "wof:placetype":"locality"
},
  "geometry": {"coordinates":[9.61849,1.38891],"type":"Point"}
}