{
  "type": "Feature",
  "properties": {
    "gn:admin1_code":"00",
    "gn:asciiname":"Mayang",
    "gn:country_code":"GQ",
    "gn:dem":68,
    "gn:feature_class":"P",
    "gn:feature_code":"PPL",
    "gn:name":"Mayang",
    "gn:population":0,
    "gn:timezone":"Africa/Malabo",
    "iso:country":"GQ",
    "wof:name":"Mayang",
    "wof:placetype":"locality"
},
  "geometry": {"coordinates":[9.84932,1.57618],"type":"Point"}
}