{
  "type": "Feature",
  "properties": {
    "gn:admin1_code":"00",
    "gn:asciiname":"Eyamoyong",
    "gn:country_code":"GQ",
    "gn:dem":716,
    "gn:feature_class":"P",
    "gn:feature_code":"PPL",
    "gn:name":"Eyamoyong",
    "gn:population":0,
    "gn:timezone":"Africa/Malabo",
    "iso:country":"GQ",
    "name:und_x_variant":[
        "Eyamayon",
        "Eyamayong",
        "Eyamoyong"
    ],
    "wof:name":"Eyamoyong",
    "wof:placetype":"locality"
},
  "geometry": {"coordinates":[10.58196,1.22527],"type":"Point"}
}