{
  "type": "Feature",
  "properties": {
    "gn:admin1_code":"00",
    "gn:asciiname":"Ebendo",
    "gn:country_code":"GQ",
    "gn:dem":12,
    "gn:feature_class":"P",
    "gn:feature_code":"PPL",
    "gn:name":"Ebendo",
    "gn:population":0,
    "gn:timezone":"Africa/Malabo",
    "iso:country":"GQ",
    "name:und_x_variant":[
        "Evende",
        "Ebendo"
    ],
    "wof:name":"Ebendo",
    "wof:placetype":"locality"
},
  "geometry": {"coordinates":[9.3133,0.89711],"type":"Point"}
}