{
  "type": "Feature",
  "properties": {
    "gn:admin1_code":"00",
    "gn:asciiname":"Bansogo",
    "gn:country_code":"GQ",
    "gn:dem":32,
    "gn:feature_class":"P",
    "gn:feature_code":"PPL",
    "gn:name":"Bansogo",
    "gn:population":0,
    "gn:timezone":"Africa/Malabo",
    "iso:country":"GQ",
    "wof:name":"Bansogo",
    "wof:placetype":"locality"
},
  "geometry": {"coordinates":[9.59729,1.52454],"type":"Point"}
}