{
  "type": "Feature",
  "properties": {
    "gn:admin1_code":"00",
    "gn:asciiname":"Mameni",
    "gn:country_code":"GQ",
    "gn:dem":504,
    "gn:feature_class":"P",
    "gn:feature_code":"PPL",
    "gn:name":"Mame\u00f1i",
    "gn:population":0,
    "gn:timezone":"Africa/Malabo",
    "iso:country":"GQ",
    "wof:name":"Mameni",
    "wof:placetype":"locality"
},
  "geometry": {"coordinates":[10.34387,2.12507],"type":"Point"}
}