{
  "type": "Feature",
  "properties": {
    "gn:admin1_code":"00",
    "gn:asciiname":"Oguama",
    "gn:country_code":"GQ",
    "gn:dem":31,
    "gn:feature_class":"P",
    "gn:feature_code":"PPL",
    "gn:name":"Oguama",
    "gn:population":0,
    "gn:timezone":"Africa/Malabo",
    "iso:country":"GQ",
    "wof:name":"Oguama",
    "wof:placetype":"locality"
},
  "geometry": {"coordinates":[9.78881,1.8373],"type":"Point"}
}