{
  "type": "Feature",
  "properties": {
    "gn:admin1_code":"00",
    "gn:asciiname":"Dyeng",
    "gn:country_code":"GQ",
    "gn:dem":146,
    "gn:feature_class":"P",
    "gn:feature_code":"PPL",
    "gn:name":"Dyeng",
    "gn:population":0,
    "gn:timezone":"Africa/Malabo",
    "iso:country":"GQ",
    "wof:name":"Dyeng",
    "wof:placetype":"locality"
},
  "geometry": {"coordinates":[10.11248,1.09117],"type":"Point"}
}