{
  "type": "Feature",
  "properties": {
    "gn:admin1_code":"00",
    "gn:asciiname":"Cnesis",
    "gn:country_code":"GQ",
    "gn:dem":659,
    "gn:feature_class":"P",
    "gn:feature_code":"PPL",
    "gn:name":"Cnesis",
    "gn:population":0,
    "gn:timezone":"Africa/Malabo",
    "iso:country":"GQ",
    "wof:name":"Cnesis",
    "wof:placetype":"locality"
},
  "geometry": {"coordinates":[11.07004,1.68861],"type":"Point"}
}