{
  "type": "Feature",
  "properties": {
    "gn:admin1_code":"00",
    "gn:asciiname":"Ebamoyong",
    "gn:country_code":"GQ",
    "gn:dem":579,
    "gn:feature_class":"P",
    "gn:feature_code":"PPL",
    "gn:name":"Ebamoyong",
    "gn:population":0,
    "gn:timezone":"Africa/Malabo",
    "iso:country":"GQ",
    "name:und_x_variant":[
        "Ebamayong",
        "Ebamoyong"
    ],
    "wof:name":"Ebamoyong",
    "wof:placetype":"locality"
},
  "geometry": {"coordinates":[10.38128,1.10114],"type":"Point"}
}