{
  "type": "Feature",
  "properties": {
    "gn:admin1_code":"00",
    "gn:asciiname":"Anisoc",
    "gn:country_code":"GQ",
    "gn:dem":668,
    "gn:feature_class":"P",
    "gn:feature_code":"PPL",
    "gn:name":"A\u00f1isoc",
    "gn:population":0,
    "gn:timezone":"Africa/Malabo",
    "iso:country":"GQ",
    "name:und_x_variant":[
        "A\u00f1isok",
        "A\u00f1isoc"
    ],
    "wof:name":"Anisoc",
    "wof:placetype":"locality"
},
  "geometry": {"coordinates":[11.10566,1.47858],"type":"Point"}
}