{
  "type": "Feature",
  "properties": {
    "gn:admin1_code":"00",
    "gn:asciiname":"Mindyimitom",
    "gn:country_code":"GQ",
    "gn:dem":610,
    "gn:feature_class":"P",
    "gn:feature_code":"PPL",
    "gn:name":"Mindyimitom",
    "gn:population":0,
    "gn:timezone":"Africa/Malabo",
    "iso:country":"GQ",
    "name:und_x_variant":[
        "Michimiton",
        "Mindyimitom"
    ],
    "wof:name":"Mindyimitom",
    "wof:placetype":"locality"
},
  "geometry": {"coordinates":[11.02541,2.11324],"type":"Point"}
}