{
  "type": "Feature",
  "properties": {
    "gn:admin1_code":"00",
    "gn:asciiname":"Ndyiacom",
    "gn:country_code":"GQ",
    "gn:dem":50,
    "gn:feature_class":"P",
    "gn:feature_code":"PPL",
    "gn:name":"Ndyiacom",
    "gn:population":0,
    "gn:timezone":"Africa/Malabo",
    "iso:country":"GQ",
    "name:und_x_variant":[
        "Ndjakom",
        "Ndyiacom"
    ],
    "wof:name":"Ndyiacom",
    "wof:placetype":"locality"
},
  "geometry": {"coordinates":[9.91353,2.03257],"type":"Point"}
}