{
  "type": "Feature",
  "properties": {
    "gn:admin1_code":"00",
    "gn:asciiname":"Too",
    "gn:country_code":"GQ",
    "gn:dem":503,
    "gn:feature_class":"P",
    "gn:feature_code":"PPL",
    "gn:name":"Too",
    "gn:population":0,
    "gn:timezone":"Africa/Malabo",
    "iso:country":"GQ",
    "wof:name":"Too",
    "wof:placetype":"locality"
},
  "geometry": {"coordinates":[10.62003,1.78889],"type":"Point"}
}