{
  "type": "Feature",
  "properties": {
    "gn:admin1_code":"00",
    "gn:asciiname":"Masa",
    "gn:country_code":"GQ",
    "gn:dem":502,
    "gn:feature_class":"P",
    "gn:feature_code":"PPL",
    "gn:name":"Masa",
    "gn:population":0,
    "gn:timezone":"Africa/Malabo",
    "iso:country":"GQ",
    "wof:name":"Masa",
    "wof:placetype":"locality"
},
  "geometry": {"coordinates":[10.52961,1.7989],"type":"Point"}
}