{
  "type": "Feature",
  "properties": {
    "gn:admin1_code":"00",
    "gn:asciiname":"Achimilang",
    "gn:country_code":"GQ",
    "gn:dem":15,
    "gn:feature_class":"P",
    "gn:feature_code":"PPL",
    "gn:name":"Achimilang",
    "gn:population":0,
    "gn:timezone":"Africa/Malabo",
    "iso:country":"GQ",
    "name:und_x_variant":[
        "Achimelang",
        "Achimilang"
    ],
    "wof:name":"Achimilang",
    "wof:placetype":"locality"
},
  "geometry": {"coordinates":[9.93242,1.01659],"type":"Point"}
}