{
  "type": "Feature",
  "properties": {
    "gn:admin1_code":"00",
    "gn:asciiname":"Bas",
    "gn:country_code":"GQ",
    "gn:dem":647,
    "gn:feature_class":"P",
    "gn:feature_code":"PPL",
    "gn:name":"Bas",
    "gn:population":0,
    "gn:timezone":"Africa/Malabo",
    "iso:country":"GQ",
    "wof:name":"Bas",
    "wof:placetype":"locality"
},
  "geometry": {"coordinates":[10.78036,1.13367],"type":"Point"}
}