{
  "type": "Feature",
  "properties": {
    "gn:admin1_code":"00",
    "gn:asciiname":"Nianam",
    "gn:country_code":"GQ",
    "gn:dem":650,
    "gn:feature_class":"P",
    "gn:feature_code":"PPL",
    "gn:name":"Nianam",
    "gn:population":0,
    "gn:timezone":"Africa/Malabo",
    "iso:country":"GQ",
    "wof:name":"Nianam",
    "wof:placetype":"locality"
},
  "geometry": {"coordinates":[11.29897,1.50015],"type":"Point"}
}