{
  "type": "Feature",
  "properties": {
    "gn:admin1_code":"00",
    "gn:asciiname":"Eduba",
    "gn:country_code":"GQ",
    "gn:dem":9,
    "gn:feature_class":"P",
    "gn:feature_code":"PPL",
    "gn:name":"Eduba",
    "gn:population":0,
    "gn:timezone":"Africa/Malabo",
    "iso:country":"GQ",
    "name:cat_x_preferred":[
        "Escola d'escribes"
    ],
    "name:hun_x_preferred":[
        "\u00c9dubba"
    ],
    "name:jpn_x_preferred":[
        "\u30a8\u30c9\u30a5\u30d6\u30d0"
    ],
    "name:spa_x_preferred":[
        "Eduba"
    ],
    "wof:name":"Eduba",
    "wof:placetype":"locality"
},
  "geometry": {"coordinates":[9.56638,1.49555],"type":"Point"}
}