{
  "type": "Feature",
  "properties": {
    "gn:admin1_code":"00",
    "gn:asciiname":"Eyamayong",
    "gn:country_code":"GQ",
    "gn:dem":687,
    "gn:feature_class":"P",
    "gn:feature_code":"PPL",
    "gn:name":"Eyamayong",
    "gn:population":0,
    "gn:timezone":"Africa/Malabo",
    "iso:country":"GQ",
    "wof:name":"Eyamayong",
    "wof:placetype":"locality"
},
  "geometry": {"coordinates":[10.93774,1.27172],"type":"Point"}
}