{
  "type": "Feature",
  "properties": {
    "gn:admin1_code":"00",
    "gn:asciiname":"Mvengayong",
    "gn:country_code":"GQ",
    "gn:dem":453,
    "gn:feature_class":"P",
    "gn:feature_code":"PPL",
    "gn:name":"Mvengayong",
    "gn:population":0,
    "gn:timezone":"Africa/Malabo",
    "iso:country":"GQ",
    "wof:name":"Mvengayong",
    "wof:placetype":"locality"
},
  "geometry": {"coordinates":[10.79718,1.95594],"type":"Point"}
}