{
  "type": "Feature",
  "properties": {
    "gn:admin1_code":"00",
    "gn:asciiname":"Afansoc",
    "gn:country_code":"GQ",
    "gn:dem":435,
    "gn:feature_class":"P",
    "gn:feature_code":"PPL",
    "gn:name":"Afansoc",
    "gn:population":0,
    "gn:timezone":"Africa/Malabo",
    "iso:country":"GQ",
    "name:und_x_variant":[
        "Afa\u2018ansok-Esong",
        "Afansoc"
    ],
    "wof:name":"Afansoc",
    "wof:placetype":"locality"
},
  "geometry": {"coordinates":[10.60175,1.8548],"type":"Point"}
}