{
  "type": "Feature",
  "properties": {
    "gn:admin1_code":"00",
    "gn:asciiname":"Nloayong",
    "gn:country_code":"GQ",
    "gn:dem":584,
    "gn:feature_class":"P",
    "gn:feature_code":"PPL",
    "gn:name":"Nloayong",
    "gn:population":0,
    "gn:timezone":"Africa/Malabo",
    "iso:country":"GQ",
    "wof:name":"Nloayong",
    "wof:placetype":"locality"
},
  "geometry": {"coordinates":[11.06943,2.15356],"type":"Point"}
}