{
  "type": "Feature",
  "properties": {
    "gn:admin1_code":"00",
    "gn:asciiname":"Bisobinam",
    "gn:country_code":"GQ",
    "gn:dem":696,
    "gn:feature_class":"P",
    "gn:feature_code":"PPL",
    "gn:name":"Bis\u00f3binam",
    "gn:population":0,
    "gn:timezone":"Africa/Malabo",
    "iso:country":"GQ",
    "wof:name":"Bisobinam",
    "wof:placetype":"locality"
},
  "geometry": {"coordinates":[11.07243,1.31961],"type":"Point"}
}