{
  "type": "Feature",
  "properties": {
    "gn:admin1_code":"00",
    "gn:asciiname":"Compania",
    "gn:country_code":"GQ",
    "gn:dem":617,
    "gn:feature_class":"P",
    "gn:feature_code":"PPL",
    "gn:name":"Compa\u00f1\u00eda",
    "gn:population":0,
    "gn:timezone":"Africa/Malabo",
    "iso:country":"GQ",
    "wof:name":"Compania",
    "wof:placetype":"locality"
},
  "geometry": {"coordinates":[10.37566,1.4533],"type":"Point"}
}