{
  "type": "Feature",
  "properties": {
    "gn:admin1_code":"00",
    "gn:asciiname":"Acalayong",
    "gn:country_code":"GQ",
    "gn:dem":640,
    "gn:feature_class":"P",
    "gn:feature_code":"PPL",
    "gn:name":"Acalayong",
    "gn:population":0,
    "gn:timezone":"Africa/Malabo",
    "iso:country":"GQ",
    "name:und_x_variant":[
        "Akalayong",
        "Acalayong"
    ],
    "wof:name":"Acalayong",
    "wof:placetype":"locality"
},
  "geometry": {"coordinates":[10.4224,1.42931],"type":"Point"}
}