{
  "type": "Feature",
  "properties": {
    "gn:admin1_code":"00",
    "gn:asciiname":"Miang",
    "gn:country_code":"GQ",
    "gn:dem":395,
    "gn:feature_class":"P",
    "gn:feature_code":"PPL",
    "gn:name":"Miang",
    "gn:population":0,
    "gn:timezone":"Africa/Malabo",
    "iso:country":"GQ",
    "wof:name":"Miang",
    "wof:placetype":"locality"
},
  "geometry": {"coordinates":[10.01839,1.22255],"type":"Point"}
}