{
  "type": "Feature",
  "properties": {
    "gn:admin1_code":"00",
    "gn:asciiname":"Nsunga",
    "gn:country_code":"GQ",
    "gn:dem":678,
    "gn:feature_class":"P",
    "gn:feature_code":"PPL",
    "gn:name":"Nsunga",
    "gn:population":0,
    "gn:timezone":"Africa/Malabo",
    "iso:country":"GQ",
    "wof:name":"Nsunga",
    "wof:placetype":"locality"
},
  "geometry": {"coordinates":[10.77134,1.54814],"type":"Point"}
}