{
  "type": "Feature",
  "properties": {
    "gn:admin1_code":"00",
    "gn:asciiname":"Maconanam",
    "gn:country_code":"GQ",
    "gn:dem":8,
    "gn:feature_class":"P",
    "gn:feature_code":"PPL",
    "gn:name":"Maconanam",
    "gn:population":0,
    "gn:timezone":"Africa/Malabo",
    "iso:country":"GQ",
    "wof:name":"Maconanam",
    "wof:placetype":"locality"
},
  "geometry": {"coordinates":[9.74747,1.76744],"type":"Point"}
}