{
  "type": "Feature",
  "properties": {
    "gn:admin1_code":"00",
    "gn:asciiname":"Mebain",
    "gn:country_code":"GQ",
    "gn:dem":681,
    "gn:feature_class":"P",
    "gn:feature_code":"PPL",
    "gn:name":"Mebai\u00f1",
    "gn:population":0,
    "gn:timezone":"Africa/Malabo",
    "iso:country":"GQ",
    "name:und_x_variant":[
        "Ebai\u00f1",
        "Mebai\u00f1"
    ],
    "wof:name":"Mebain",
    "wof:placetype":"locality"
},
  "geometry": {"coordinates":[10.58825,1.51685],"type":"Point"}
}