{
  "type": "Feature",
  "properties": {
    "gn:admin1_code":"00",
    "gn:asciiname":"Alep",
    "gn:country_code":"GQ",
    "gn:dem":51,
    "gn:feature_class":"P",
    "gn:feature_code":"PPL",
    "gn:name":"Alep",
    "gn:population":0,
    "gn:timezone":"Africa/Malabo",
    "iso:country":"GQ",
    "wof:name":"Alep",
    "wof:placetype":"locality"
},
  "geometry": {"coordinates":[9.85872,2.11158],"type":"Point"}
}