{
  "type": "Feature",
  "properties": {
    "gn:admin1_code":"00",
    "gn:asciiname":"Angon",
    "gn:country_code":"GQ",
    "gn:dem":680,
    "gn:feature_class":"P",
    "gn:feature_code":"PPL",
    "gn:name":"Angon",
    "gn:population":0,
    "gn:timezone":"Africa/Malabo",
    "iso:country":"GQ",
    "wof:name":"Angon",
    "wof:placetype":"locality"
},
  "geometry": {"coordinates":[10.89694,1.28719],"type":"Point"}
}