{
  "type": "Feature",
  "properties": {
    "gn:admin1_code":"00",
    "gn:asciiname":"Dum",
    "gn:country_code":"GQ",
    "gn:dem":101,
    "gn:feature_class":"P",
    "gn:feature_code":"PPL",
    "gn:name":"Dum",
    "gn:population":0,
    "gn:timezone":"Africa/Malabo",
    "iso:country":"GQ",
    "wof:name":"Dum",
    "wof:placetype":"locality"
},
  "geometry": {"coordinates":[9.99005,2.06454],"type":"Point"}
}