{
  "type": "Feature",
  "properties": {
    "gn:admin1_code":"00",
    "gn:asciiname":"Afaanam",
    "gn:country_code":"GQ",
    "gn:dem":664,
    "gn:feature_class":"P",
    "gn:feature_code":"PPL",
    "gn:name":"Afaanam",
    "gn:population":0,
    "gn:timezone":"Africa/Malabo",
    "iso:country":"GQ",
    "name:und_x_variant":[
        "Afa\u2019annam",
        "Afaanam"
    ],
    "wof:name":"Afaanam",
    "wof:placetype":"locality"
},
  "geometry": {"coordinates":[10.98108,1.32771],"type":"Point"}
}