{
  "type": "Feature",
  "properties": {
    "gn:admin1_code":"00",
    "gn:asciiname":"Matuin",
    "gn:country_code":"GQ",
    "gn:dem":664,
    "gn:feature_class":"P",
    "gn:feature_code":"PPL",
    "gn:name":"Matui\u00f1",
    "gn:population":0,
    "gn:timezone":"Africa/Malabo",
    "iso:country":"GQ",
    "name:und_x_variant":[
        "Metui",
        "Matui\u00f1"
    ],
    "wof:name":"Matuin",
    "wof:placetype":"locality"
},
  "geometry": {"coordinates":[11.11916,1.67932],"type":"Point"}
}